<?xml version="1.0" encoding="utf-8" standalone="yes"?><sld g="dbf73251-abaf-49e1-8df7-0623a291dc96" verG="a3f918db-338f-4bcd-911c-c44b6422b1d8" timeManagerVisibilityLocked="true" typeName="" id="0" state="0" showMasterSp="false" name="Scenario 3 - SITUACIÓN" role="" resetMode="auto" layoutG="344c570e-67fa-4bbc-a9a9-10b7169a90b0" stateG="00000000-0000-0000-0000-000000000000" showPlay="false" clrScheme="def" isDrawingThemeUpgraded="true" assetG="00000000-0000-0000-0000-000000000000" backVis="trans" layoutType="Content" hideToc="false" advMode="user" linkType="none" showInReview="true" includeInSlideCounts="true" zoomTransDur="1000" useNextTrans="true"><tmProps g="0677e597-dc33-46d6-b64c-a7cd24ff1ab5" verG="449366ee-7710-4af8-ab94-e6e4d70a84bb" cur="0" min="10000" visible="true" hideAll="false"><markers nextId="0" /></tmProps><tmCtxLst version="1"><tmCtx g="c90b910b-6c7c-43de-91cc-95e63541678c" verG="d2f107c6-d7dd-4dee-ac3c-069d5c5cc00d" start="0" dur="3000" min="250" max="0" hasMax="false" alwysShw="false" untilEnd="false" assetStart="0" name="" /></tmCtxLst><sz w="0" h="0" /><trans /><bg><lineStyle w="0" scale="1" cap="def" join="def" dash="cstm" cmpnd="cstm"><arrow scale="1"><begin type="def" sz="def" /><end type="def" sz="def" /></arrow></lineStyle></bg><shapeLst><rect g="f288c826-6f0b-4e94-a4f0-4bd9277bc9e9" verG="31ebc45a-79ea-462e-8f19-de7b66da37c0" timeManagerVisibilityLocked="false" typeName="" id="1" name="Rectángulo" state="111367" zOrder="0" editCtx="Normal" initState="" handCur="true" rot="-1" acc="true" autoFit="none" shdw="false" wrap="true" rtl="false" defHorzAlign="c" horzAlign="c" vertAlign="m" textDir="horz"><tmProps g="eaf59ac0-991a-4d11-9acf-312119f09cc1" verG="3e7b131f-56a3-41c6-bf2f-f259b145dce5" cur="0" min="5000" visible="true" hideAll="false" /><tmCtxLst version="2"><txtTmCtx g="19e67381-dce8-4412-ab57-1d70d14fe1b1" verG="4e8e9ed3-26a5-436c-96fd-463a63d099d4" start="0" dur="10000" min="250" max="0" hasMax="false" alwysShw="false" untilEnd="true" assetStart="0" name="" /></tmCtxLst><animEffect /><childLst /><trigLst /><stateLst /><bG shine="false"><solidFill><clr><srgbClr val="058A9E" /></clr></solidFill><noLine /><lineStyle w="1.38888884" scale="1.38888884" cap="flat" join="rnd" dash="sld" cmpnd="sng"><arrow scale="1.38888884"><begin type="none" sz="size5" /><end type="none" sz="size5" /></arrow></lineStyle><gradOvrlyFill type="lin" style="lin" rot="true" angle="90" blendMode="ovrly" alpha="1" scale="1" reverse="false" adjustY="0" overlayFillType="None"><centerPt x="1" y="1" /><fillRect l="0" t="0" r="0" b="0" /><stops /></gradOvrlyFill><shdw sz="100" blur="5" angle="90" dist="5"><preset val="noShdw" mode="noShdw" /><clr><srgbClr val="000000" /><alpha val="43137" /></clr></shdw><reflection type="none" /><glow type="none" spread="0"><clr><schemeClr val="accent1" /></clr></glow><softEdge type="none" spread="0" /><foreClr><schemeClr val="lt1" /></foreClr></bG><sldSz w="1000" h="580" /><loc l="7.41789055" t="5.638889" r="992.5821" b="574.361145" /><hLink enabled="false" trigG="00000000-0000-0000-0000-000000000000" /><fmtText></fmtText><propBag><prop><key>oldsize</key><val><sz w="1000" h="580" /></val></prop></propBag><dialData dialType="None" varG="00000000-0000-0000-0000-000000000000" defVarG="00000000-0000-0000-0000-000000000000" updateAction="drag" increment="1" rotation="180" rotationIndicatorOffsetDegrees="0" indicatorPaintMode="Always"><values start="0" end="12" /><rotationPoint xOffset="0" yOffset="0" /></dialData><textMargin l="13" t="5" r="13" b="5" /><bounds l="0" t="0" r="0" b="0" /><resize fontNm="" fontSz="0" /><margins l="0" t="0" r="0" b="0" /><parLst /><plain></plain><hLinkLst /></rect><pic g="65f02026-301f-4adf-ab14-c98c750b419d" verG="649d16fa-b33e-45ff-96b7-2eff8bd7ee51" timeManagerVisibilityLocked="false" typeName="" id="2" name="Imagen" state="107335" zOrder="1" editCtx="Normal" initState="" handCur="true" rot="-1" acc="true" assetG="e74b1203-ad6d-4dab-ba7b-a231979af589" imgSet="true" blend="srcCpy" useFileName="true" freeForm="false"><tmProps g="4029a873-e265-4fd3-8bed-cf497dbed155" verG="309477f4-ca84-440f-98ab-7cd3f0977544" cur="0" min="5000" visible="true" hideAll="false" /><tmCtxLst version="2"><tmCtx g="5df14f02-7efa-4d9d-9d5b-de8c72a9ad7e" verG="8ec888ef-a8fd-4b91-a091-7033403fcb40" start="0" dur="10000" min="250" max="0" hasMax="false" alwysShw="false" untilEnd="true" assetStart="0" name="" /></tmCtxLst><animEffect /><childLst /><trigLst /><stateLst /><bG shine="false"><noFill /><noLine /><lineStyle w="3" scale="1" cap="flat" join="rnd" dash="sld" cmpnd="sng"><arrow scale="1"><begin type="none" sz="size5" /><end type="none" sz="size5" /></arrow></lineStyle><gradOvrlyFill type="lin" style="lin" rot="true" angle="90" blendMode="ovrly" alpha="1" scale="1" reverse="false" adjustY="0" overlayFillType="None"><centerPt x="1" y="1" /><fillRect l="0" t="0" r="0" b="0" /><stops /></gradOvrlyFill><shdw sz="100" blur="4" angle="90" dist="4"><preset val="noShdw" mode="noShdw" /><clr><srgbClr val="000000" /><alpha val="60000" /></clr></shdw><reflection type="none" /><glow type="none" spread="0"><clr><schemeClr val="accent1" /></clr></glow><softEdge type="none" spread="0" /><foreClr><schemeClr val="dk1" /></foreClr></bG><sldSz w="1000" h="580" /><loc l="14" t="122" r="986" b="568" /><hLink enabled="false" trigG="00000000-0000-0000-0000-000000000000" /><fmtText></fmtText><propBag><prop><key>oldsize</key><val><sz w="1000" h="580" /></val></prop></propBag><dialData dialType="None" varG="00000000-0000-0000-0000-000000000000" defVarG="00000000-0000-0000-0000-000000000000" updateAction="drag" increment="1" rotation="180" rotationIndicatorOffsetDegrees="0" indicatorPaintMode="Always"><values start="0" end="12" /><rotationPoint xOffset="0" yOffset="0" /></dialData><picFormat tile="true" trans="0" rot="true"><offset l="0" t="0" r="0" b="0" /><tile x="0" y="0" scaleX="100" scaleY="100" align="1" mirror="Tile">Clamp</tile><sourceRect l="0" t="0" r="128" b="128" /><pic><brightness val="Normal" level="0" /><contrast val="Normal" level="0" /><recolor val="None"><clr /></recolor><blend mode="norm"><clr /></blend></pic></picFormat></pic><pic g="cdb6f0b2-d8e2-454b-8769-f8b1dda2d4bb" verG="200f1988-7352-4ffb-b604-9f39c15c69fd" timeManagerVisibilityLocked="false" typeName="" id="1" name="Imagen" state="111431" zOrder="2" editCtx="Normal" initState="" handCur="true" rot="-1" acc="true" assetG="5261872f-8be6-4fa5-81fa-8172c33afdab" imgSet="true" blend="srcCpy" useFileName="true" freeForm="false"><tmProps g="62071234-6bbf-49be-a4ea-8a675e93ede2" verG="645d2b93-6129-416a-8b02-23fe2c29545a" cur="0" min="5000" visible="true" hideAll="false" /><tmCtxLst version="2"><tmCtx g="b0e87f86-e4ea-45fa-9599-0f15b29fe4c6" verG="963505ef-f38b-492f-aabe-fe0a02d0051f" start="0" dur="10000" min="250" max="0" hasMax="false" alwysShw="false" untilEnd="true" assetStart="0" name="" /></tmCtxLst><animEffect /><childLst /><trigLst /><stateLst /><bG shine="false"><noFill /><noLine /><lineStyle w="4.16666651" scale="1.38888884" cap="flat" join="rnd" dash="sld" cmpnd="sng"><arrow scale="1.38888884"><begin type="none" sz="size5" /><end type="none" sz="size5" /></arrow></lineStyle><gradOvrlyFill type="lin" style="lin" rot="true" angle="90" blendMode="ovrly" alpha="1" scale="1" reverse="false" adjustY="0" overlayFillType="None"><centerPt x="1" y="1" /><fillRect l="0" t="0" r="0" b="0" /><stops /></gradOvrlyFill><shdw sz="100" blur="4" angle="90" dist="4"><preset val="noShdw" mode="noShdw" /><clr><srgbClr val="000000" /><alpha val="60000" /></clr></shdw><reflection type="none" /><glow type="none" spread="0"><clr><schemeClr val="accent1" /></clr></glow><softEdge type="none" spread="0" /><foreClr><schemeClr val="dk1" /></foreClr></bG><sldSz w="1000" h="580" /><loc l="32.13379" t="21.37268" r="260.460022" b="94.62731" /><hLink enabled="false" trigG="00000000-0000-0000-0000-000000000000" /><fmtText></fmtText><propBag><prop><key>oldsize</key><val><sz w="1000" h="580" /></val></prop></propBag><dialData dialType="None" varG="00000000-0000-0000-0000-000000000000" defVarG="00000000-0000-0000-0000-000000000000" updateAction="drag" increment="1" rotation="180" rotationIndicatorOffsetDegrees="0" indicatorPaintMode="Always"><values start="0" end="12" /><rotationPoint xOffset="0" yOffset="0" /></dialData><picFormat tile="true" trans="0" rot="true"><offset l="0" t="0" r="0" b="0" /><tile x="0" y="0" scaleX="100" scaleY="100" align="1" mirror="Tile">Clamp</tile><sourceRect l="0" t="0" r="128" b="128" /><pic><brightness val="Normal" level="0" /><contrast val="Normal" level="0" /><recolor val="None"><clr /></recolor><blend mode="norm"><clr /></blend></pic></picFormat></pic><rect g="6dc695ef-4b05-48d0-9094-73dd38c1aa30" verG="3338adc3-4cbb-44b5-a7fb-e074150e198f" timeManagerVisibilityLocked="false" typeName="" id="2" name="Rectangle" state="106759" zOrder="3" editCtx="Normal" initState="" handCur="true" rot="-1" acc="true" autoFit="none" shdw="false" wrap="true" rtl="false" defHorzAlign="c" horzAlign="c" vertAlign="m" textDir="horz" defHorzOvr="c"><tmProps g="84668a50-61c8-4c94-a230-c5dfc42212c0" verG="2f38e149-6ffa-4e84-927f-6145a1447cb7" cur="0" min="5000" visible="true" hideAll="false" /><tmCtxLst version="2"><txtTmCtx g="9f4a2607-0677-415a-a371-043d9a5b9eb6" verG="04048405-c2a4-4e32-ba84-4e75923ffc01" start="0" dur="10000" min="250" max="0" hasMax="false" alwysShw="false" untilEnd="true" assetStart="0" name="" /></tmCtxLst><animEffect><entr><fade dur="PT1S" lvl="none" easingDir="none" easingType="lin" dir="none" /></entr></animEffect><childLst /><trigLst /><stateLst /><bG shine="false"><noFill /><noLine /><lineStyle w="1.92901218" scale="1.38888884" cap="flat" join="rnd" dash="sld" cmpnd="sng"><arrow scale="1.38888884"><begin type="none" sz="size5" /><end type="none" sz="size5" /></arrow></lineStyle><gradOvrlyFill type="lin" style="lin" rot="true" angle="90" blendMode="ovrly" alpha="1" scale="1" reverse="false" adjustY="0" overlayFillType="None"><centerPt x="1" y="1" /><fillRect l="0" t="0" r="0" b="0" /><stops /></gradOvrlyFill><shdw sz="100" blur="5" angle="0" dist="4"><preset val="offR" mode="offR" /><clr><srgbClr val="000000" /><alpha val="30196" /></clr></shdw><reflection type="none" /><glow type="none" spread="0"><clr><schemeClr val="accent1" /></clr></glow><softEdge type="none" spread="0" /><foreClr><schemeClr val="lt1" /></foreClr><defaultFont name="+minor" sz="10.5" style="Regular" cap="none"><clr><schemeClr val="dk1" /></clr></defaultFont></bG><sldSz w="1000" h="580" /><loc l="289.804321" t="18.2592583" r="992.5821" b="97.74074" /><hLink enabled="false" trigG="00000000-0000-0000-0000-000000000000" /><text>&lt;Document xmlns:xsi="http://www.w3.org/2001/XMLSchema-instance" xmlns:xsd="http://www.w3.org/2001/XMLSchema"&gt;
  &lt;Content&gt;
    &lt;Block&gt;
      &lt;Style Justification="Left" /&gt;
      &lt;Span Text="SITUACIÓN"&gt;
        &lt;Style FontFamily="Open Sans" FontSize="10.08" FontIsBold="True" ForegroundColor="lt1,00" LinkColor="lt1,00" /&gt;
      &lt;/Span&gt;
      &lt;Span Text=": Mujer joven que nos pide algo para la irritación de los ojos porque nos informa que usa lentillas y se nota tirantez, escozor, ardor… Incluso le parece que ve menos con las lentillas."&gt;
        &lt;Style FontSize="10.08" ForegroundColor="lt1,00" LinkColor="lt1,00" /&gt;
      &lt;/Span&gt;
    &lt;/Block&gt;
  &lt;/Content&gt;
&lt;/Document&gt;</text><fmtText>&lt;Document xmlns:xsi="http://www.w3.org/2001/XMLSchema-instance" xmlns:xsd="http://www.w3.org/2001/XMLSchema"&gt;
  &lt;Content&gt;
    &lt;Block&gt;
      &lt;Style FlowDirection="LeftToRight" LeadingMargin="0" TrailingMargin="0" FirstLineMargin="0" Justification="Left" DefaultTabStop="48" CustomTabStops="" ListLevel="0" LineSpacingRule="Multiple" LineSpacing="20" SpacingBefore="0" SpacingAfter="0"&gt;
        &lt;BaseSpanStyle FontFamily="+minor" FontSize="10.5" FontIsBold="False" FontIsItalic="False" FontIsUnderline="False" FontIsStrikeout="False" UnderlineStyle="Normal" ForegroundColor="dk1,00" BackgroundColor="#000000,00" UnderlineColor="#000000,00" Elevation="Normal" Spacing="0" IgnoreKerningTable="False" DisplayCase="AsIs" LanguageId="0" LinkColor="#0000FF"&gt;
          &lt;Shadow Offset="0x0" Color="#FFFFFF,00" /&gt;
        &lt;/BaseSpanStyle&gt;
        &lt;ListStyle ListType="None" ListTypeFormat="Plain" Start="0" Color="#000000,00" Size="100" /&gt;
      &lt;/Style&gt;
      &lt;Span Text="SITUACIÓN"&gt;
        &lt;Style FontFamily="Open Sans" FontSize="10.08" FontIsBold="True" FontIsItalic="False" FontIsUnderline="False" FontIsStrikeout="False" UnderlineStyle="Normal" ForegroundColor="#000000" BackgroundColor="#000000,00" UnderlineColor="#000000,00" Elevation="Normal" Spacing="0" IgnoreKerningTable="False" DisplayCase="AsIs" LanguageId="0" LinkColor="#000000"&gt;
          &lt;Shadow Offset="0x0" Color="#FFFFFF,00" /&gt;
        &lt;/Style&gt;
      &lt;/Span&gt;
      &lt;Span Text=": Hombre de mediana edad que acude a la farmacia con dos recetas en las que se prescriben un colirio y una pomada oftálmica, ambas para tratar una infección ocular. "&gt;
        &lt;Style FontFamily="Open Sans" FontSize="10.08" FontIsBold="False" FontIsItalic="False" FontIsUnderline="False" FontIsStrikeout="False" UnderlineStyle="Normal" ForegroundColor="#000000" BackgroundColor="#000000,00" UnderlineColor="#000000,00" Elevation="Normal" Spacing="0" IgnoreKerningTable="False" DisplayCase="AsIs" LanguageId="0" LinkColor="#000000"&gt;
          &lt;Shadow Offset="0x0" Color="#FFFFFF,00" /&gt;
        &lt;/Style&gt;
      &lt;/Span&gt;
    &lt;/Block&gt;
  &lt;/Content&gt;
&lt;/Document&gt;</fmtText><propBag><prop><key>oldsize</key><val><sz w="1000" h="580" /></val></prop></propBag><dialData dialType="None" varG="00000000-0000-0000-0000-000000000000" defVarG="00000000-0000-0000-0000-000000000000" updateAction="drag" increment="1" rotation="180" rotationIndicatorOffsetDegrees="0" indicatorPaintMode="Always"><values start="0" end="12" /><rotationPoint xOffset="0" yOffset="0" /></dialData><textMargin l="10" t="5" r="10" b="5" /><bounds l="11" t="5" r="694" b="74" /><resize fontNm="" fontSz="0" /><margins l="0" t="0" r="0" b="0" /><parLst /><plain>SITUACIÓN: Mujer joven que nos pide algo para la irritación de los ojos porque nos informa que usa lentillas y se nota tirantez, escozor, ardor… Incluso le parece que ve menos con las lentillas.</plain><hLinkLst /></rect><diamond g="625f5d64-dbfa-4b4e-980a-e8188feed501" verG="0b55f52a-6e05-4322-94f9-fd09d27086b1" timeManagerVisibilityLocked="false" typeName="" id="1" name="Diamond" state="107271" zOrder="4" editCtx="Normal" initState="" handCur="true" rot="-1" acc="true" autoFit="def" shdw="none" wrap="none" rtl="false" defHorzAlign="l" horzAlign="not" vertAlign="not" textDir="not"><tmProps g="f8d45233-6250-4bae-8508-0a26f67c2360" verG="9c4736ff-cb4a-4207-b918-69406628e20c" cur="0" min="5000" visible="true" hideAll="false" /><tmCtxLst version="2"><txtTmCtx g="b6670673-60a2-4d14-bc86-64bb1dedafc8" verG="ed3abc87-68e7-4d96-8b44-19a27d078548" start="0" dur="10000" min="250" max="0" hasMax="false" alwysShw="false" untilEnd="true" assetStart="0" name="" /></tmCtxLst><animEffect><entr><zoom dur="PT1S" lvl="none" easingDir="none" easingType="lin" vp="shp" /></entr></animEffect><childLst /><trigLst /><stateLst /><bG><solidFill><clr><schemeClr val="lt1" /></clr></solidFill><solidLine><clr><schemeClr val="lt1" /></clr></solidLine><lineStyle w="1" scale="1" cap="def" join="def" dash="cstm" cmpnd="cstm"><arrow scale="1"><begin type="def" sz="def" /><end type="def" sz="def" /></arrow></lineStyle><gradOvrlyFill type="def" style="def" rot="none" angle="3.40282347E+38" blendMode="def" alpha="-1" scale="-1" reverse="none" adjustY="-2147483648" overlayFillType="None"><centerPt x="-1" y="-1" /><fillRect l="0" t="0" r="0" b="0" /><stops /></gradOvrlyFill><shdw sz="100" blur="5" angle="90" dist="5"><preset val="noShdw" mode="noShdw" /><clr><srgbClr val="000000" /><alpha val="43137" /></clr></shdw><foreClr><schemeClr val="lt1" /></foreClr></bG><sldSz w="1000" h="580" /><loc l="282" t="21" r="287" b="94.62731" /><hLink enabled="false" trigG="00000000-0000-0000-0000-000000000000" /><prstGeom><diamond vertexSet="false" /></prstGeom><dialData dialType="None" varG="00000000-0000-0000-0000-000000000000" defVarG="00000000-0000-0000-0000-000000000000" updateAction="drag" increment="1" rotation="180" rotationIndicatorOffsetDegrees="0" indicatorPaintMode="Always"><values start="0" end="12" /><rotationPoint xOffset="0" yOffset="0" /></dialData><textMargin l="-1" t="-1" r="-1" b="-1" /><bounds l="0" t="0" r="0" b="0" /><resize fontNm="" fontSz="0" /><margins l="0" t="0" r="0" b="0" /><parLst /><plain></plain><hLinkLst /></diamond><marker g="11da698a-0b20-43d2-ab56-4e7d1e46bc1a" verG="47141184-00dc-44b9-9b57-82aa361c5ce5" timeManagerVisibilityLocked="false" typeName="" id="1" name="Marker" state="107015" zOrder="5" editCtx="Normal" initState="" handCur="true" rot="-1" acc="true" autoFit="resize" shdw="false" wrap="false" rtl="false" defHorzAlign="l" horzAlign="l" vertAlign="t" textDir="horz"><tmProps g="935f9cf0-a438-4062-87bb-dc64267506ec" verG="d1707a6c-7dbe-4761-bfd9-5ec5c72506cc" cur="0" min="5000" visible="true" hideAll="false" /><tmCtxLst version="2"><txtTmCtx g="0599d2db-7182-4b32-b7d8-f952a2010830" verG="e50eabf4-f205-45ad-8c8f-541424803f36" start="0" dur="10000" min="250" max="0" hasMax="false" alwysShw="false" untilEnd="true" assetStart="0" name="" /></tmCtxLst><animEffect /><childLst /><trigLst><trig g="49737f30-846e-4569-9bc8-0e0782b54719" verG="ac350d48-ae85-4e0a-b5d0-30ae84dd9f83" name="" type="user" edit="all" group="none" copiedG="11da698a-0b20-43d2-ab56-4e7d1e46bc1a"><data enabled="true" event="OnMouseHover" action="changeShapeState" actSubType="next" NavigationIntent="Unspecified" NavigationState="None"><keyPress keys="None" case="false" /><slide showNav="false" /><scene /><shape setStateG="c3022a67-2f31-4a8b-8cda-6853ae07e94d" setStateName="Normal" stateInclude="all" statesNot="are" stateName=""><stateLst /><dropLst /><intersectLst /><stopIntersectLst /><hoverLst /></shape><clickLst /><sldLayer /><video /><audio /><other open="" email="" js="" op="ass" varVal1="" useVar="false" dblVal="0" boolVal="True" positiveCompletion="true" time="PT0S" cuePoint="-2147483648" useRandom="false" randomMin="0" randomMax="0" /><interaction /><SeekTimeline target="00000000-0000-0000-0000-000000000000" timeSeconds="0" cuePoint="-1" variableReference="false" useRelativeTime="false" relativeTime="NaN" modifyPlaybackState="false" playbackState="Play" /><frame restore="false" /></data><condLst /></trig></trigLst><stateLst /><bG shine="false"><solidFill><clr><srgbClr val="AA9C8F" /></clr></solidFill><solidLine><clr><srgbClr val="AA9C8F" /></clr></solidLine><lineStyle w="1" scale="1" cap="flat" join="rnd" dash="sld" cmpnd="sng"><arrow scale="1"><begin type="none" sz="size5" /><end type="none" sz="size5" /></arrow></lineStyle><gradOvrlyFill type="lin" style="lin" rot="true" angle="90" blendMode="ovrly" alpha="1" scale="1" reverse="false" adjustY="0" overlayFillType="None"><centerPt x="1" y="1" /><fillRect l="0" t="0" r="0" b="0" /><stops /></gradOvrlyFill><shdw sz="100" blur="5" angle="90" dist="5"><preset val="noShdw" mode="noShdw" /><clr><srgbClr val="000000" /><alpha val="43137" /></clr></shdw><reflection type="none" /><glow type="none" spread="0"><clr><schemeClr val="accent1" /></clr></glow><softEdge type="none" spread="0" /><foreClr><schemeClr val="lt1" /></foreClr></bG><sldSz w="1000" h="580" /><loc l="196.460022" t="255" r="224.460022" b="283" /><hLink enabled="false" trigG="00000000-0000-0000-0000-000000000000" /><fmtText></fmtText><propBag><prop><key>oldsize</key><val><sz w="1000" h="580" /></val></prop></propBag><dialData dialType="None" varG="00000000-0000-0000-0000-000000000000" defVarG="00000000-0000-0000-0000-000000000000" updateAction="drag" increment="1" rotation="180" rotationIndicatorOffsetDegrees="0" indicatorPaintMode="Always"><values start="0" end="12" /><rotationPoint xOffset="0" yOffset="0" /></dialData><textMargin l="10" t="5" r="10" b="5" /><bounds l="0" t="0" r="0" b="0" /><resize fontNm="+minor" fontSz="12" /><margins l="0" t="0" r="0" b="0" /><parLst /><plain></plain><markerProps pos="tc" ani="plse" clsOthrs="true" audioOnly="false" shwHvr="true" mute="false" vol="50" lblW="230" lblH="117" picto="Number1"><contentBg shine="false"><solidFill><clr><srgbClr val="AA9C8F" /></clr></solidFill><noLine /><lineStyle w="1" scale="1" cap="flat" join="rnd" dash="sld" cmpnd="sng"><arrow scale="1"><begin type="none" sz="size5" /><end type="none" sz="size5" /></arrow></lineStyle><gradOvrlyFill type="lin" style="lin" rot="true" angle="90" blendMode="ovrly" alpha="1" scale="1" reverse="false" adjustY="0" overlayFillType="None"><centerPt x="1" y="1" /><fillRect l="0" t="0" r="0" b="0" /><stops /></gradOvrlyFill><shdw sz="100" blur="3" angle="90" dist="2"><preset val="none" mode="noShdw" /><clr><srgbClr val="000000" /><alpha val="36862" /></clr></shdw><reflection type="none" /><glow type="none" spread="0"><clr><schemeClr val="accent1" /></clr></glow><softEdge type="none" spread="0" /><foreClr><schemeClr val="lt1" /></foreClr></contentBg><ttlBnds l="106" t="56" r="378" b="81" /><descBnds l="93" t="144" r="383" b="209" /><pnlBnds l="0" t="0" r="200" b="100" /><media pos="bc" assetG="00000000-0000-0000-0000-000000000000" url=""><loc l="0" t="0" r="267" b="66" /><sz w="0" h="0" /><video g="0b18e134-90cc-4202-b2f7-eca5db01716a" verG="e05984cd-dce6-494b-b547-3920325eab8d" timeManagerVisibilityLocked="false" typeName="" id="0" name="Video" state="106567" zOrder="-1" editCtx="Normal" initState="" handCur="true" rot="-1" acc="true" autoFit="none" shdw="false" wrap="false" rtl="false" defHorzAlign="l" horzAlign="l" vertAlign="t" textDir="horz" ansG="23edd626-c27e-4f83-b49a-c5c629b56d55" canDel="true" canCopy="true" codec="unk" play="auto" vol="50" mute="false" showCtrls="false" full="false" loop="false" rew="false" thumbType="int" mode="vid" compressOnPublish="true" vidDispMode="sld" brwsrDispMode="none" vidSrcType="local" vidG="00000000-0000-0000-0000-000000000000" origThumbG="00000000-0000-0000-0000-000000000000" thumbG="00000000-0000-0000-0000-000000000000" flvG="00000000-0000-0000-0000-000000000000" srcG="00000000-0000-0000-0000-000000000000"><tmProps g="4175ac69-8554-44a0-b003-3a08e2e5862a" verG="d81a52c1-46d0-4895-97df-4795fa40da4c" cur="0" min="5000" visible="true" hideAll="false" /><tmCtxLst version="1"><vidTmCtx g="5b5e4638-528c-4443-9bb2-b60791bedd61" verG="6a1a92ec-de65-4c40-b4a0-bf89b980afee" start="0" dur="3000" min="250" max="0" hasMax="false" alwysShw="false" untilEnd="false" assetStart="0" name="" /></tmCtxLst><animEffect /><childLst /><trigLst /><stateLst /><bG shine="false"><noFill /><noLine /><gradOvrlyFill type="lin" style="lin" rot="true" angle="90" blendMode="ovrly" alpha="1" scale="1" reverse="false" adjustY="0" overlayFillType="None"><centerPt x="1" y="1" /><fillRect l="0" t="0" r="0" b="0" /><stops /></gradOvrlyFill><shdw sz="100" blur="5" angle="90" dist="5"><preset val="noShdw" mode="noShdw" /><clr><srgbClr val="000000" /><alpha val="43137" /></clr></shdw><reflection type="none" /><glow type="none" spread="0"><clr><schemeClr val="accent1" /></clr></glow><softEdge type="none" spread="0" /><foreClr><schemeClr val="dk1" /></foreClr></bG><sldSz w="720" h="540" /><loc l="0" t="0" r="108" b="38" /><hLink enabled="false" trigG="00000000-0000-0000-0000-000000000000" /><fmtText></fmtText><dialData dialType="None" varG="00000000-0000-0000-0000-000000000000" defVarG="00000000-0000-0000-0000-000000000000" updateAction="drag" increment="1" rotation="180" rotationIndicatorOffsetDegrees="0" indicatorPaintMode="Always"><values start="0" end="12" /><rotationPoint xOffset="0" yOffset="0" /></dialData><textMargin l="10" t="5" r="10" b="5" /><bounds l="0" t="0" r="0" b="0" /><resize fontNm="" fontSz="0" /><parLst /><movie dur="0" fps="30"><sz w="0" h="0" /></movie><embed></embed><url></url></video><pic g="fa0a6eaf-f448-41f9-a0c8-024e1a34819d" verG="56bc512d-b5e8-44ec-875d-14c4756c5996" timeManagerVisibilityLocked="false" typeName="" id="0" name="Picture" state="106567" zOrder="-1" editCtx="Normal" initState="" handCur="true" rot="-1" acc="true" imgSet="false" blend="srcCpy" useFileName="true" freeForm="false"><tmProps g="68edb4af-4961-4390-bc0a-1d4b2bccae1e" verG="5a6c0ffa-d7d5-4902-be3c-b1e60cf826c5" cur="0" min="5000" visible="true" hideAll="false" /><tmCtxLst version="1"><tmCtx g="30cdb5ba-e97c-4445-a5e3-1e41a2cd1f98" verG="5fd04802-f2ad-4db4-b33a-d43e5c6ad209" start="0" dur="3000" min="250" max="0" hasMax="false" alwysShw="false" untilEnd="false" assetStart="0" name="" /></tmCtxLst><animEffect /><childLst /><trigLst /><stateLst /><bG shine="false"><noFill /><noLine /><gradOvrlyFill type="lin" style="lin" rot="true" angle="90" blendMode="ovrly" alpha="1" scale="1" reverse="false" adjustY="0" overlayFillType="None"><centerPt x="1" y="1" /><fillRect l="0" t="0" r="0" b="0" /><stops /></gradOvrlyFill><shdw sz="100" blur="4" angle="90" dist="4"><preset val="noShdw" mode="noShdw" /><clr><srgbClr val="000000" /><alpha val="60000" /></clr></shdw><reflection type="none" /><glow type="none" spread="0"><clr><schemeClr val="accent1" /></clr></glow><softEdge type="none" spread="0" /><foreClr><schemeClr val="dk1" /></foreClr></bG><sldSz w="720" h="540" /><loc l="0" t="0" r="74" b="74" /><hLink enabled="false" trigG="00000000-0000-0000-0000-000000000000" /><fmtText></fmtText><dialData dialType="None" varG="00000000-0000-0000-0000-000000000000" defVarG="00000000-0000-0000-0000-000000000000" updateAction="drag" increment="1" rotation="180" rotationIndicatorOffsetDegrees="0" indicatorPaintMode="Always"><values start="0" end="12" /><rotationPoint xOffset="0" yOffset="0" /></dialData><picFormat tile="true" trans="0" rot="true"><offset l="0" t="0" r="0" b="0" /><tile x="0" y="0" scaleX="100" scaleY="100" align="1" mirror="Tile">Clamp</tile><sourceRect l="0" t="0" r="128" b="128" /><pic><brightness val="Normal" level="0" /><contrast val="Normal" level="0" /><recolor val="None"><clr /></recolor><blend mode="norm"><clr /></blend></pic></picFormat></pic></media><title></title><desc>&lt;Document xmlns:xsi="http://www.w3.org/2001/XMLSchema-instance" xmlns:xsd="http://www.w3.org/2001/XMLSchema"&gt;
  &lt;Content&gt;
    &lt;Block&gt;
      &lt;Style FlowDirection="LeftToRight" LeadingMargin="0" TrailingMargin="0" FirstLineMargin="0" Justification="Justify" LineSpacingRule="Multiple" LineSpacing="20" SpacingBefore="0" SpacingAfter="0"&gt;
        &lt;ListStyle ListType="None" ListTypeFormat="Parentheses" BulletFont="Arial" /&gt;
      &lt;/Style&gt;
      &lt;Span Text="Necesito algún "&gt;
        &lt;Style FontFamily="Open Sans" FontSize="8.64" FontIsBold="False" FontIsItalic="False" FontIsUnderline="False" FontIsStrikeout="False" ForegroundColor="#FFFFFF" /&gt;
      &lt;/Span&gt;
      &lt;Span Text="colirio"&gt;
        &lt;Style FontFamily="Open Sans" FontSize="8.64" FontIsBold="True" FontIsItalic="False" FontIsUnderline="False" FontIsStrikeout="False" ForegroundColor="#FFFF00" LinkColor="#FFFF00" /&gt;
      &lt;/Span&gt;
      &lt;Span Text=" o algo que me calme este escozor y malestar en los ojos."&gt;
        &lt;Style FontFamily="Open Sans" FontSize="8.64" FontIsBold="False" FontIsItalic="False" FontIsUnderline="False" FontIsStrikeout="False" ForegroundColor="#FFFFFF" /&gt;
      &lt;/Span&gt;
    &lt;/Block&gt;
  &lt;/Content&gt;
&lt;/Document&gt;</desc><ttlShp g="029ca911-76db-4a04-a11c-a3ff4d2c4216" verG="c14ec647-fd06-42fa-ad5a-ec777663bfa7" timeManagerVisibilityLocked="false" typeName="" id="0" name="Text Box" state="106759" zOrder="-1" editCtx="Normal" initState="" handCur="true" rot="-1" acc="true" autoFit="resize" shdw="false" wrap="true" rtl="false" defHorzAlign="l" horzAlign="l" vertAlign="m" textDir="horz"><tmProps g="252db9c8-f9d1-406d-83f2-2d729a18f1d8" verG="546de596-64d2-44af-b4dc-a1a4e5c99142" cur="0" min="5000" visible="true" hideAll="false" /><tmCtxLst version="1"><txtTmCtx g="e2a77d56-059d-40af-b725-55cbd516c9da" verG="baec3ee2-eb2d-4055-a72a-37dc9fdb5d36" start="0" dur="3000" min="250" max="0" hasMax="false" alwysShw="false" untilEnd="false" assetStart="0" name="" /></tmCtxLst><animEffect /><childLst /><trigLst /><stateLst /><bG shine="false"><noFill /><noLine /><lineStyle w="3" scale="1" cap="flat" join="rnd" dash="sld" cmpnd="sng"><arrow scale="1"><begin type="none" sz="size5" /><end type="none" sz="size5" /></arrow></lineStyle><gradOvrlyFill type="lin" style="lin" rot="true" angle="90" blendMode="ovrly" alpha="1" scale="1" reverse="false" adjustY="0" overlayFillType="None"><centerPt x="1" y="1" /><fillRect l="0" t="0" r="0" b="0" /><stops /></gradOvrlyFill><shdw sz="100" blur="4" angle="90" dist="4"><preset val="noShdw" mode="noShdw" /><clr><srgbClr val="000000" /><alpha val="60000" /></clr></shdw><reflection type="none" /><glow type="none" spread="0"><clr><schemeClr val="accent1" /></clr></glow><softEdge type="none" spread="0" /><foreClr><schemeClr val="dk1" /></foreClr><defaultFont sz="10" style="Bold" /></bG><sldSz w="720" h="540" /><loc l="0" t="0" r="3" b="10" /><hLink enabled="false" trigG="00000000-0000-0000-0000-000000000000" /><fmtText></fmtText><ph type="title" /><dialData dialType="None" varG="00000000-0000-0000-0000-000000000000" defVarG="00000000-0000-0000-0000-000000000000" updateAction="drag" increment="1" rotation="180" rotationIndicatorOffsetDegrees="0" indicatorPaintMode="Always"><values start="0" end="12" /><rotationPoint xOffset="0" yOffset="0" /></dialData><textMargin l="0" t="0" r="0" b="0" /><bounds l="0" t="0" r="0" b="0" /><resize fontNm="" fontSz="0" /><margins l="0" t="0" r="0" b="0" /><parLst /><plain></plain><hLinkLst /></ttlShp><descShp g="2fb199fc-dd98-4ed8-b299-d408e9e207b4" verG="9c7e5dd4-1c0c-4298-99e8-9d7e139e4634" timeManagerVisibilityLocked="false" typeName="" id="0" name="Text Box" state="106759" zOrder="0" editCtx="Normal" initState="" handCur="true" rot="-1" acc="true" parentG="d1f4ac6c-054a-442c-93ce-821a96b89736" autoFit="resize" shdw="false" wrap="true" rtl="false" defHorzAlign="l" horzAlign="l" vertAlign="t" textDir="horz"><tmProps g="28be0893-5f30-4927-ac17-24779738810b" verG="59b0f8cc-f0af-46e3-8588-3cbe77349d67" cur="0" min="5000" visible="true" hideAll="false" /><tmCtxLst version="1"><txtTmCtx g="2bbd0a8f-cc42-43f7-b7f8-5c5182471ef8" verG="1bb3ca40-9beb-49e6-af71-c43a8e5b16e8" start="0" dur="3000" min="250" max="0" hasMax="false" alwysShw="false" untilEnd="false" assetStart="0" name="" /></tmCtxLst><animEffect /><childLst /><trigLst /><stateLst /><bG shine="false"><noFill /><noLine /><lineStyle w="3" scale="1" cap="flat" join="rnd" dash="sld" cmpnd="sng"><arrow scale="1"><begin type="none" sz="size5" /><end type="none" sz="size5" /></arrow></lineStyle><gradOvrlyFill type="lin" style="lin" rot="true" angle="90" blendMode="ovrly" alpha="1" scale="1" reverse="false" adjustY="0" overlayFillType="None"><centerPt x="1" y="1" /><fillRect l="0" t="0" r="0" b="0" /><stops /></gradOvrlyFill><shdw sz="100" blur="4" angle="90" dist="4"><preset val="noShdw" mode="noShdw" /><clr><srgbClr val="000000" /><alpha val="60000" /></clr></shdw><reflection type="none" /><glow type="none" spread="0"><clr><schemeClr val="accent1" /></clr></glow><softEdge type="none" spread="0" /><foreClr><schemeClr val="dk1" /></foreClr><defaultFont sz="8.25" style="Regular" /></bG><sldSz w="1000" h="580" /><loc l="27" t="151" r="565" b="194" /><hLink enabled="false" trigG="00000000-0000-0000-0000-000000000000" /><fmtText></fmtText><ph type="body" /><dialData dialType="None" varG="00000000-0000-0000-0000-000000000000" defVarG="00000000-0000-0000-0000-000000000000" updateAction="drag" increment="1" rotation="180" rotationIndicatorOffsetDegrees="0" indicatorPaintMode="Always"><values start="0" end="12" /><rotationPoint xOffset="0" yOffset="0" /></dialData><textMargin l="0" t="0" r="0" b="0" /><bounds l="0" t="0" r="220" b="65" /><resize fontNm="" fontSz="0" /><margins l="0" t="0" r="0" b="0" /><parLst /><plain>Necesito algún colirio o algo que me calme este escozor y malestar en los ojos.</plain><hLinkLst /></descShp></markerProps></marker><marker g="c3022a67-2f31-4a8b-8cda-6853ae07e94d" verG="9abb48e4-937c-415d-8233-aa80e9030791" timeManagerVisibilityLocked="false" typeName="" id="2" name="Marker" state="107015" zOrder="6" editCtx="Normal" initState="Hidden" handCur="true" rot="-1" acc="true" autoFit="resize" shdw="false" wrap="false" rtl="false" defHorzAlign="l" horzAlign="l" vertAlign="t" textDir="horz"><tmProps g="518af163-0f09-4b5e-b584-93bb857f4aff" verG="9d121f62-1b55-4b9f-bc9f-dbc499f9fd8b" cur="0" min="5000" visible="true" hideAll="false" /><tmCtxLst version="2"><txtTmCtx g="fbadfa14-55bf-4a95-955c-6afdac7165c7" verG="52ee2b47-83e7-4aae-a16e-17ff4fb3547f" start="0" dur="10000" min="250" max="0" hasMax="false" alwysShw="false" untilEnd="true" assetStart="0" name="" /></tmCtxLst><animEffect /><childLst /><trigLst><trig g="306ff090-b5ac-44ab-91ee-8d96b2d66870" verG="fb4adc69-ef93-4124-9155-e0948b8cf32f" name="" type="user" edit="all" group="none" copiedG="c3022a67-2f31-4a8b-8cda-6853ae07e94d"><data enabled="true" event="OnMouseHover" action="changeShapeState" actSubType="next" NavigationIntent="Unspecified" NavigationState="None"><keyPress keys="None" case="false" /><slide showNav="false" /><scene /><shape setStateG="74a3aa28-fe8a-4df6-8310-dcb8eaf2304d" setStateName="Normal" stateInclude="all" statesNot="are" stateName=""><stateLst /><dropLst /><intersectLst /><stopIntersectLst /><hoverLst /></shape><clickLst /><sldLayer /><video /><audio /><other open="" email="" js="" op="ass" varVal1="" useVar="false" dblVal="0" boolVal="True" positiveCompletion="true" time="PT0S" cuePoint="-2147483648" useRandom="false" randomMin="0" randomMax="0" /><interaction /><SeekTimeline target="00000000-0000-0000-0000-000000000000" timeSeconds="0" cuePoint="-1" variableReference="false" useRelativeTime="false" relativeTime="NaN" modifyPlaybackState="false" playbackState="Play" /><frame restore="false" /></data><condLst /></trig></trigLst><stateLst /><bG shine="false"><solidFill><clr><srgbClr val="078A9E" /></clr></solidFill><solidLine><clr><srgbClr val="078A9E" /></clr></solidLine><lineStyle w="1" scale="1" cap="flat" join="rnd" dash="sld" cmpnd="sng"><arrow scale="1"><begin type="none" sz="size5" /><end type="none" sz="size5" /></arrow></lineStyle><gradOvrlyFill type="lin" style="lin" rot="true" angle="90" blendMode="ovrly" alpha="1" scale="1" reverse="false" adjustY="0" overlayFillType="None"><centerPt x="1" y="1" /><fillRect l="0" t="0" r="0" b="0" /><stops /></gradOvrlyFill><shdw sz="100" blur="5" angle="90" dist="5"><preset val="noShdw" mode="noShdw" /><clr><srgbClr val="000000" /><alpha val="43137" /></clr></shdw><reflection type="none" /><glow type="none" spread="0"><clr><schemeClr val="accent1" /></clr></glow><softEdge type="none" spread="0" /><foreClr><schemeClr val="lt1" /></foreClr></bG><sldSz w="1000" h="580" /><loc l="679" t="317" r="707" b="345" /><hLink enabled="false" trigG="00000000-0000-0000-0000-000000000000" /><fmtText></fmtText><propBag><prop><key>oldsize</key><val><sz w="1000" h="580" /></val></prop></propBag><dialData dialType="None" varG="00000000-0000-0000-0000-000000000000" defVarG="00000000-0000-0000-0000-000000000000" updateAction="drag" increment="1" rotation="180" rotationIndicatorOffsetDegrees="0" indicatorPaintMode="Always"><values start="0" end="12" /><rotationPoint xOffset="0" yOffset="0" /></dialData><textMargin l="10" t="5" r="10" b="5" /><bounds l="0" t="0" r="0" b="0" /><resize fontNm="+minor" fontSz="12" /><margins l="0" t="0" r="0" b="0" /><parLst /><plain></plain><markerProps pos="tc" ani="plse" clsOthrs="true" audioOnly="false" shwHvr="true" mute="false" vol="50" lblW="272" lblH="157" picto="Number2"><contentBg shine="false"><solidFill><clr><srgbClr val="078A9E" /></clr></solidFill><noLine /><lineStyle w="1" scale="1" cap="flat" join="rnd" dash="sld" cmpnd="sng"><arrow scale="1"><begin type="none" sz="size5" /><end type="none" sz="size5" /></arrow></lineStyle><gradOvrlyFill type="lin" style="lin" rot="true" angle="90" blendMode="ovrly" alpha="1" scale="1" reverse="false" adjustY="0" overlayFillType="None"><centerPt x="1" y="1" /><fillRect l="0" t="0" r="0" b="0" /><stops /></gradOvrlyFill><shdw sz="100" blur="3" angle="90" dist="2"><preset val="none" mode="noShdw" /><clr><srgbClr val="000000" /><alpha val="36862" /></clr></shdw><reflection type="none" /><glow type="none" spread="0"><clr><schemeClr val="accent1" /></clr></glow><softEdge type="none" spread="0" /><foreClr><schemeClr val="lt1" /></foreClr></contentBg><ttlBnds l="609" t="34" r="935" b="59" /><descBnds l="506" t="193" r="880" b="301" /><pnlBnds l="0" t="0" r="200" b="100" /><media pos="bc" assetG="00000000-0000-0000-0000-000000000000" url=""><loc l="0" t="0" r="147" b="64.5" /><sz w="0" h="0" /><video g="1597d98a-1dfe-483d-8b0f-901ff6621f56" verG="f87ed13e-873f-4d74-bbfe-02a468caa431" timeManagerVisibilityLocked="false" typeName="" id="0" name="Video" state="106567" zOrder="-1" editCtx="Normal" initState="" handCur="true" rot="-1" acc="true" autoFit="none" shdw="false" wrap="false" rtl="false" defHorzAlign="l" horzAlign="l" vertAlign="t" textDir="horz" ansG="e4e0939e-7a49-4803-80c1-f0768831c82a" canDel="true" canCopy="true" codec="unk" play="auto" vol="50" mute="false" showCtrls="false" full="false" loop="false" rew="false" thumbType="int" mode="vid" compressOnPublish="true" vidDispMode="sld" brwsrDispMode="none" vidSrcType="local" vidG="00000000-0000-0000-0000-000000000000" origThumbG="00000000-0000-0000-0000-000000000000" thumbG="00000000-0000-0000-0000-000000000000" flvG="00000000-0000-0000-0000-000000000000" srcG="00000000-0000-0000-0000-000000000000"><tmProps g="0c90560e-5a70-4417-aa6f-3957e438a3b5" verG="356fec87-87c4-44e1-8b77-e83ecf2c3df5" cur="0" min="5000" visible="true" hideAll="false" /><tmCtxLst version="1"><vidTmCtx g="6cab3270-8f96-4604-aaeb-4f923042f976" verG="83406a12-9013-467b-9f0f-78ade1d78a5d" start="0" dur="3000" min="250" max="0" hasMax="false" alwysShw="false" untilEnd="false" assetStart="0" name="" /></tmCtxLst><animEffect /><childLst /><trigLst /><stateLst /><bG shine="false"><noFill /><noLine /><gradOvrlyFill type="lin" style="lin" rot="true" angle="90" blendMode="ovrly" alpha="1" scale="1" reverse="false" adjustY="0" overlayFillType="None"><centerPt x="1" y="1" /><fillRect l="0" t="0" r="0" b="0" /><stops /></gradOvrlyFill><shdw sz="100" blur="5" angle="90" dist="5"><preset val="noShdw" mode="noShdw" /><clr><srgbClr val="000000" /><alpha val="43137" /></clr></shdw><reflection type="none" /><glow type="none" spread="0"><clr><schemeClr val="accent1" /></clr></glow><softEdge type="none" spread="0" /><foreClr><schemeClr val="dk1" /></foreClr></bG><sldSz w="720" h="540" /><loc l="0" t="0" r="108" b="38" /><hLink enabled="false" trigG="00000000-0000-0000-0000-000000000000" /><fmtText></fmtText><dialData dialType="None" varG="00000000-0000-0000-0000-000000000000" defVarG="00000000-0000-0000-0000-000000000000" updateAction="drag" increment="1" rotation="180" rotationIndicatorOffsetDegrees="0" indicatorPaintMode="Always"><values start="0" end="12" /><rotationPoint xOffset="0" yOffset="0" /></dialData><textMargin l="10" t="5" r="10" b="5" /><bounds l="0" t="0" r="0" b="0" /><resize fontNm="" fontSz="0" /><parLst /><movie dur="0" fps="30"><sz w="0" h="0" /></movie><embed></embed><url></url></video><pic g="714c2fbe-1e32-46ee-92b9-a68a5808c400" verG="e28b3594-a6a7-4add-ad16-7ef9b61b5999" timeManagerVisibilityLocked="false" typeName="" id="0" name="Picture" state="106567" zOrder="-1" editCtx="Normal" initState="" handCur="true" rot="-1" acc="true" imgSet="false" blend="srcCpy" useFileName="true" freeForm="false"><tmProps g="014c6b01-ef98-4d45-9b8b-29246b8691f3" verG="33bba0a9-c58e-416a-b936-b3a7844daab4" cur="0" min="5000" visible="true" hideAll="false" /><tmCtxLst version="1"><tmCtx g="484415be-73a1-421a-a99a-aa26196cb239" verG="3678c3c2-ce1f-4a11-95ed-be0e60d0fe0f" start="0" dur="3000" min="250" max="0" hasMax="false" alwysShw="false" untilEnd="false" assetStart="0" name="" /></tmCtxLst><animEffect /><childLst /><trigLst /><stateLst /><bG shine="false"><noFill /><noLine /><gradOvrlyFill type="lin" style="lin" rot="true" angle="90" blendMode="ovrly" alpha="1" scale="1" reverse="false" adjustY="0" overlayFillType="None"><centerPt x="1" y="1" /><fillRect l="0" t="0" r="0" b="0" /><stops /></gradOvrlyFill><shdw sz="100" blur="4" angle="90" dist="4"><preset val="noShdw" mode="noShdw" /><clr><srgbClr val="000000" /><alpha val="60000" /></clr></shdw><reflection type="none" /><glow type="none" spread="0"><clr><schemeClr val="accent1" /></clr></glow><softEdge type="none" spread="0" /><foreClr><schemeClr val="dk1" /></foreClr></bG><sldSz w="720" h="540" /><loc l="0" t="0" r="74" b="74" /><hLink enabled="false" trigG="00000000-0000-0000-0000-000000000000" /><fmtText></fmtText><dialData dialType="None" varG="00000000-0000-0000-0000-000000000000" defVarG="00000000-0000-0000-0000-000000000000" updateAction="drag" increment="1" rotation="180" rotationIndicatorOffsetDegrees="0" indicatorPaintMode="Always"><values start="0" end="12" /><rotationPoint xOffset="0" yOffset="0" /></dialData><picFormat tile="true" trans="0" rot="true"><offset l="0" t="0" r="0" b="0" /><tile x="0" y="0" scaleX="100" scaleY="100" align="1" mirror="Tile">Clamp</tile><sourceRect l="0" t="0" r="128" b="128" /><pic><brightness val="Normal" level="0" /><contrast val="Normal" level="0" /><recolor val="None"><clr /></recolor><blend mode="norm"><clr /></blend></pic></picFormat></pic></media><title></title><desc>&lt;Document xmlns:xsi="http://www.w3.org/2001/XMLSchema-instance" xmlns:xsd="http://www.w3.org/2001/XMLSchema"&gt;
  &lt;Content&gt;
    &lt;Block&gt;
      &lt;Style FlowDirection="LeftToRight" LeadingMargin="0" TrailingMargin="0" FirstLineMargin="0" Justification="Center" LineSpacingRule="Multiple" LineSpacing="20" SpacingBefore="0" SpacingAfter="0"&gt;
        &lt;ListStyle ListType="None" ListTypeFormat="Parentheses" BulletFont="Arial" /&gt;
      &lt;/Style&gt;
      &lt;Span Text="¿Empeoras a lo largo del día? &amp;#xA;"&gt;
        &lt;Style FontFamily="Open Sans" FontSize="8.64" FontIsBold="False" FontIsItalic="False" FontIsUnderline="False" FontIsStrikeout="False" ForegroundColor="#FFFFFF" /&gt;
      &lt;/Span&gt;
    &lt;/Block&gt;
    &lt;Block&gt;
      &lt;Style FlowDirection="LeftToRight" LeadingMargin="0" TrailingMargin="0" FirstLineMargin="0" Justification="Center" LineSpacingRule="Multiple" LineSpacing="20" SpacingBefore="0" SpacingAfter="0"&gt;
        &lt;ListStyle ListType="None" ListTypeFormat="Parentheses" BulletFont="Arial" /&gt;
      &lt;/Style&gt;
      &lt;Span Text="¿Se te agudizan los síntomas si estás en un ambiente cargado?&amp;#xA;"&gt;
        &lt;Style FontFamily="Open Sans" FontSize="8.64" FontIsBold="True" FontIsItalic="False" FontIsUnderline="False" FontIsStrikeout="False" ForegroundColor="#FFFF00" LinkColor="#FFFF00" /&gt;
      &lt;/Span&gt;
    &lt;/Block&gt;
    &lt;Block&gt;
      &lt;Style FlowDirection="LeftToRight" LeadingMargin="0" TrailingMargin="0" FirstLineMargin="0" Justification="Center" LineSpacingRule="Multiple" LineSpacing="20" SpacingBefore="0" SpacingAfter="0"&gt;
        &lt;ListStyle ListType="None" ListTypeFormat="Parentheses" BulletFont="Arial" /&gt;
      &lt;/Style&gt;
      &lt;Span Text=" "&gt;
        &lt;Style FontFamily="Open Sans" FontSize="8.64" FontIsBold="True" FontIsItalic="False" FontIsUnderline="False" FontIsStrikeout="False" ForegroundColor="#FFFF00" LinkColor="#FFFF00" /&gt;
      &lt;/Span&gt;
      &lt;Span Text="¿Miras mucho el móvil, el ordenador, la tablet, etc?"&gt;
        &lt;Style FontFamily="Open Sans" FontSize="8.64" FontIsBold="False" FontIsItalic="False" FontIsUnderline="False" FontIsStrikeout="False" ForegroundColor="#FFFFFF" /&gt;
      &lt;/Span&gt;
    &lt;/Block&gt;
  &lt;/Content&gt;
&lt;/Document&gt;</desc><ttlShp g="c521e878-9442-4f45-a29a-4479fa15935a" verG="3204485d-9a48-4026-a0f7-aacb074a2486" timeManagerVisibilityLocked="false" typeName="" id="0" name="Text Box" state="106759" zOrder="-1" editCtx="Normal" initState="" handCur="true" rot="-1" acc="true" autoFit="resize" shdw="false" wrap="true" rtl="false" defHorzAlign="l" horzAlign="l" vertAlign="m" textDir="horz"><tmProps g="2bd33917-a594-46de-ae8a-e9ddf51cc947" verG="9922c774-c406-4380-85f3-1ddfbcd67086" cur="0" min="5000" visible="true" hideAll="false" /><tmCtxLst version="1"><txtTmCtx g="99b70377-9dc5-43fd-962f-66b57228134d" verG="eddb5a36-9380-4a21-895b-1d7a17d02d07" start="0" dur="3000" min="250" max="0" hasMax="false" alwysShw="false" untilEnd="false" assetStart="0" name="" /></tmCtxLst><animEffect /><childLst /><trigLst /><stateLst /><bG shine="false"><noFill /><noLine /><lineStyle w="3" scale="1" cap="flat" join="rnd" dash="sld" cmpnd="sng"><arrow scale="1"><begin type="none" sz="size5" /><end type="none" sz="size5" /></arrow></lineStyle><gradOvrlyFill type="lin" style="lin" rot="true" angle="90" blendMode="ovrly" alpha="1" scale="1" reverse="false" adjustY="0" overlayFillType="None"><centerPt x="1" y="1" /><fillRect l="0" t="0" r="0" b="0" /><stops /></gradOvrlyFill><shdw sz="100" blur="4" angle="90" dist="4"><preset val="noShdw" mode="noShdw" /><clr><srgbClr val="000000" /><alpha val="60000" /></clr></shdw><reflection type="none" /><glow type="none" spread="0"><clr><schemeClr val="accent1" /></clr></glow><softEdge type="none" spread="0" /><foreClr><schemeClr val="dk1" /></foreClr><defaultFont sz="10" style="Bold" /></bG><sldSz w="720" h="540" /><loc l="0" t="0" r="3" b="10" /><hLink enabled="false" trigG="00000000-0000-0000-0000-000000000000" /><fmtText></fmtText><ph type="title" /><dialData dialType="None" varG="00000000-0000-0000-0000-000000000000" defVarG="00000000-0000-0000-0000-000000000000" updateAction="drag" increment="1" rotation="180" rotationIndicatorOffsetDegrees="0" indicatorPaintMode="Always"><values start="0" end="12" /><rotationPoint xOffset="0" yOffset="0" /></dialData><textMargin l="0" t="0" r="0" b="0" /><bounds l="0" t="0" r="0" b="0" /><resize fontNm="" fontSz="0" /><margins l="0" t="0" r="0" b="0" /><parLst /><plain></plain><hLinkLst /></ttlShp><descShp g="c47b69de-2d56-44c4-bc60-5205ec4f39f6" verG="b607d463-ce06-47fe-8b3f-5bf1b29e63ab" timeManagerVisibilityLocked="false" typeName="" id="0" name="Text Box" state="106759" zOrder="0" editCtx="Normal" initState="" handCur="true" rot="-1" acc="true" parentG="fb61d027-0e00-4a80-9fc0-db948856f2bb" autoFit="resize" shdw="false" wrap="true" rtl="false" defHorzAlign="l" horzAlign="l" vertAlign="t" textDir="horz"><tmProps g="2df9d48e-3308-4396-b0a4-11daf90e27ed" verG="dd924851-dc2d-4ca7-b015-ad8a18687dd3" cur="0" min="5000" visible="true" hideAll="false" /><tmCtxLst version="1"><txtTmCtx g="558aff54-b549-4c23-8133-88759a6a4f4a" verG="59a39544-f6e0-4281-8328-92d0315a6d75" start="0" dur="3000" min="250" max="0" hasMax="false" alwysShw="false" untilEnd="false" assetStart="0" name="" /></tmCtxLst><animEffect /><childLst /><trigLst /><stateLst /><bG shine="false"><noFill /><noLine /><lineStyle w="3" scale="1" cap="flat" join="rnd" dash="sld" cmpnd="sng"><arrow scale="1"><begin type="none" sz="size5" /><end type="none" sz="size5" /></arrow></lineStyle><gradOvrlyFill type="lin" style="lin" rot="true" angle="90" blendMode="ovrly" alpha="1" scale="1" reverse="false" adjustY="0" overlayFillType="None"><centerPt x="1" y="1" /><fillRect l="0" t="0" r="0" b="0" /><stops /></gradOvrlyFill><shdw sz="100" blur="4" angle="90" dist="4"><preset val="noShdw" mode="noShdw" /><clr><srgbClr val="000000" /><alpha val="60000" /></clr></shdw><reflection type="none" /><glow type="none" spread="0"><clr><schemeClr val="accent1" /></clr></glow><softEdge type="none" spread="0" /><foreClr><schemeClr val="dk1" /></foreClr><defaultFont sz="8.25" style="Regular" /></bG><sldSz w="1000" h="580" /><loc l="506" t="193" r="880" b="301" /><hLink enabled="false" trigG="00000000-0000-0000-0000-000000000000" /><fmtText></fmtText><ph type="body" /><dialData dialType="None" varG="00000000-0000-0000-0000-000000000000" defVarG="00000000-0000-0000-0000-000000000000" updateAction="drag" increment="1" rotation="180" rotationIndicatorOffsetDegrees="0" indicatorPaintMode="Always"><values start="0" end="12" /><rotationPoint xOffset="0" yOffset="0" /></dialData><textMargin l="0" t="0" r="0" b="0" /><bounds l="0" t="0" r="262" b="108" /><resize fontNm="" fontSz="0" /><margins l="0" t="0" r="0" b="0" /><parLst /><plain>¿Empeoras a lo largo del día? 
¿Se te agudizan los síntomas si estás en un ambiente cargado?
 ¿Miras mucho el móvil, el ordenador, la tablet, etc?</plain><hLinkLst /></descShp></markerProps></marker><marker g="74a3aa28-fe8a-4df6-8310-dcb8eaf2304d" verG="9963bf38-c2d4-470e-b7e1-be260f937984" timeManagerVisibilityLocked="false" typeName="" id="3" name="Marker" state="107015" zOrder="7" editCtx="Normal" initState="Hidden" handCur="true" rot="-1" acc="true" autoFit="resize" shdw="false" wrap="false" rtl="false" defHorzAlign="l" horzAlign="l" vertAlign="t" textDir="horz"><tmProps g="f3137cb0-a056-412d-be9b-4c8b2bb5f5d6" verG="f3705d88-0a4f-4a2f-afbf-a216eb88a592" cur="0" min="5000" visible="true" hideAll="false" /><tmCtxLst version="2"><txtTmCtx g="3600dffb-e4dd-4ed2-87ba-3c96608c1d37" verG="47fe5d90-4d42-46c5-90ae-1aaea71e10bc" start="0" dur="10000" min="250" max="0" hasMax="false" alwysShw="false" untilEnd="true" assetStart="0" name="" /></tmCtxLst><animEffect /><childLst /><trigLst><trig g="07cb586c-71df-47cc-a218-30d8b1ccc121" verG="68850046-ce60-4a4d-a834-163bed0fcdef" name="" type="user" edit="all" group="none" copiedG="74a3aa28-fe8a-4df6-8310-dcb8eaf2304d"><data enabled="true" event="OnMouseHover" action="changeShapeState" actSubType="next" NavigationIntent="Unspecified" NavigationState="None"><keyPress keys="None" case="false" /><slide showNav="false" /><scene /><shape setStateG="46878305-d980-43ad-a601-aba31aefcf98" setStateName="Normal" stateInclude="all" statesNot="are" stateName=""><stateLst /><dropLst /><intersectLst /><stopIntersectLst /><hoverLst /></shape><clickLst /><sldLayer /><video /><audio /><other open="" email="" js="" op="ass" varVal1="" useVar="false" dblVal="0" boolVal="True" positiveCompletion="true" time="PT0S" cuePoint="-2147483648" useRandom="false" randomMin="0" randomMax="0" /><interaction /><SeekTimeline target="00000000-0000-0000-0000-000000000000" timeSeconds="0" cuePoint="-1" variableReference="false" useRelativeTime="false" relativeTime="NaN" modifyPlaybackState="false" playbackState="Play" /><frame restore="false" /></data><condLst /></trig></trigLst><stateLst /><bG shine="false"><solidFill><clr><srgbClr val="928D88" /></clr></solidFill><solidLine><clr><srgbClr val="AA9C8F" /></clr></solidLine><lineStyle w="1" scale="1" cap="flat" join="rnd" dash="sld" cmpnd="sng"><arrow scale="1"><begin type="none" sz="size5" /><end type="none" sz="size5" /></arrow></lineStyle><gradOvrlyFill type="lin" style="lin" rot="true" angle="90" blendMode="ovrly" alpha="1" scale="1" reverse="false" adjustY="0" overlayFillType="None"><centerPt x="1" y="1" /><fillRect l="0" t="0" r="0" b="0" /><stops /></gradOvrlyFill><shdw sz="100" blur="5" angle="90" dist="5"><preset val="noShdw" mode="noShdw" /><clr><srgbClr val="000000" /><alpha val="43137" /></clr></shdw><reflection type="none" /><glow type="none" spread="0"><clr><schemeClr val="accent1" /></clr></glow><softEdge type="none" spread="0" /><foreClr><schemeClr val="lt1" /></foreClr></bG><sldSz w="1000" h="580" /><loc l="196.460022" t="444" r="224.460022" b="472" /><hLink enabled="false" trigG="00000000-0000-0000-0000-000000000000" /><fmtText></fmtText><propBag><prop><key>oldsize</key><val><sz w="1000" h="580" /></val></prop></propBag><dialData dialType="None" varG="00000000-0000-0000-0000-000000000000" defVarG="00000000-0000-0000-0000-000000000000" updateAction="drag" increment="1" rotation="180" rotationIndicatorOffsetDegrees="0" indicatorPaintMode="Always"><values start="0" end="12" /><rotationPoint xOffset="0" yOffset="0" /></dialData><textMargin l="10" t="5" r="10" b="5" /><bounds l="0" t="0" r="0" b="0" /><resize fontNm="+minor" fontSz="12" /><margins l="0" t="0" r="0" b="0" /><parLst /><plain></plain><markerProps pos="tc" ani="plse" clsOthrs="true" audioOnly="false" shwHvr="true" mute="false" vol="50" lblW="288" lblH="175" picto="Number3"><contentBg shine="false"><solidFill><clr><srgbClr val="AA9C8F" /></clr></solidFill><noLine /><lineStyle w="1" scale="1" cap="flat" join="rnd" dash="sld" cmpnd="sng"><arrow scale="1"><begin type="none" sz="size5" /><end type="none" sz="size5" /></arrow></lineStyle><gradOvrlyFill type="lin" style="lin" rot="true" angle="90" blendMode="ovrly" alpha="1" scale="1" reverse="false" adjustY="0" overlayFillType="None"><centerPt x="1" y="1" /><fillRect l="0" t="0" r="0" b="0" /><stops /></gradOvrlyFill><shdw sz="100" blur="3" angle="90" dist="2"><preset val="none" mode="noShdw" /><clr><srgbClr val="000000" /><alpha val="36862" /></clr></shdw><reflection type="none" /><glow type="none" spread="0"><clr><schemeClr val="accent1" /></clr></glow><softEdge type="none" spread="0" /><foreClr><schemeClr val="lt1" /></foreClr></contentBg><ttlBnds l="108" t="116" r="354" b="141" /><descBnds l="71" t="221" r="349" b="329" /><pnlBnds l="0" t="0" r="200" b="100" /><media pos="bc" assetG="00000000-0000-0000-0000-000000000000" url=""><loc l="0" t="0" r="138" b="103" /><sz w="0" h="0" /><video g="1e55797e-27bb-403f-8efd-6cb1a52c8773" verG="243c550b-9c09-48a6-ae24-a338b159b686" timeManagerVisibilityLocked="false" typeName="" id="0" name="Video" state="106567" zOrder="-1" editCtx="Normal" initState="" handCur="true" rot="-1" acc="true" autoFit="none" shdw="false" wrap="false" rtl="false" defHorzAlign="l" horzAlign="l" vertAlign="t" textDir="horz" ansG="66ac2fa6-d4c4-4e1e-97da-fbe29a25b0b3" canDel="true" canCopy="true" codec="unk" play="auto" vol="50" mute="false" showCtrls="false" full="false" loop="false" rew="false" thumbType="int" mode="vid" compressOnPublish="true" vidDispMode="sld" brwsrDispMode="none" vidSrcType="local" vidG="00000000-0000-0000-0000-000000000000" origThumbG="00000000-0000-0000-0000-000000000000" thumbG="00000000-0000-0000-0000-000000000000" flvG="00000000-0000-0000-0000-000000000000" srcG="00000000-0000-0000-0000-000000000000"><tmProps g="0a68dd84-aca7-4274-a816-246830280184" verG="4e9eaa90-74d9-4c06-a80b-03b9c85c3fd1" cur="0" min="5000" visible="true" hideAll="false" /><tmCtxLst version="1"><vidTmCtx g="6dbca1eb-d202-4f0b-9958-62ed9e4ea4b6" verG="3e32d820-fcbe-40c1-9feb-99ee05b30566" start="0" dur="3000" min="250" max="0" hasMax="false" alwysShw="false" untilEnd="false" assetStart="0" name="" /></tmCtxLst><animEffect /><childLst /><trigLst /><stateLst /><bG shine="false"><noFill /><noLine /><gradOvrlyFill type="lin" style="lin" rot="true" angle="90" blendMode="ovrly" alpha="1" scale="1" reverse="false" adjustY="0" overlayFillType="None"><centerPt x="1" y="1" /><fillRect l="0" t="0" r="0" b="0" /><stops /></gradOvrlyFill><shdw sz="100" blur="5" angle="90" dist="5"><preset val="noShdw" mode="noShdw" /><clr><srgbClr val="000000" /><alpha val="43137" /></clr></shdw><reflection type="none" /><glow type="none" spread="0"><clr><schemeClr val="accent1" /></clr></glow><softEdge type="none" spread="0" /><foreClr><schemeClr val="dk1" /></foreClr></bG><sldSz w="720" h="540" /><loc l="0" t="0" r="108" b="38" /><hLink enabled="false" trigG="00000000-0000-0000-0000-000000000000" /><fmtText></fmtText><dialData dialType="None" varG="00000000-0000-0000-0000-000000000000" defVarG="00000000-0000-0000-0000-000000000000" updateAction="drag" increment="1" rotation="180" rotationIndicatorOffsetDegrees="0" indicatorPaintMode="Always"><values start="0" end="12" /><rotationPoint xOffset="0" yOffset="0" /></dialData><textMargin l="10" t="5" r="10" b="5" /><bounds l="0" t="0" r="0" b="0" /><resize fontNm="" fontSz="0" /><parLst /><movie dur="0" fps="30"><sz w="0" h="0" /></movie><embed></embed><url></url></video><pic g="fa6e1d29-7343-40ed-a994-d2a421711729" verG="80337f81-58f6-4cef-be4b-16bff2f49c86" timeManagerVisibilityLocked="false" typeName="" id="0" name="Picture" state="106567" zOrder="-1" editCtx="Normal" initState="" handCur="true" rot="-1" acc="true" imgSet="false" blend="srcCpy" useFileName="true" freeForm="false"><tmProps g="f67d172d-bdaf-46bc-a66b-794d2b314e79" verG="3669ba5b-8801-4c38-b9a3-158f6cc58f71" cur="0" min="5000" visible="true" hideAll="false" /><tmCtxLst version="1"><tmCtx g="83219a52-f867-4acc-9c3a-b45b4d8c8de2" verG="58106708-06a9-4de8-95b1-dc12593db4fb" start="0" dur="3000" min="250" max="0" hasMax="false" alwysShw="false" untilEnd="false" assetStart="0" name="" /></tmCtxLst><animEffect /><childLst /><trigLst /><stateLst /><bG shine="false"><noFill /><noLine /><gradOvrlyFill type="lin" style="lin" rot="true" angle="90" blendMode="ovrly" alpha="1" scale="1" reverse="false" adjustY="0" overlayFillType="None"><centerPt x="1" y="1" /><fillRect l="0" t="0" r="0" b="0" /><stops /></gradOvrlyFill><shdw sz="100" blur="4" angle="90" dist="4"><preset val="noShdw" mode="noShdw" /><clr><srgbClr val="000000" /><alpha val="60000" /></clr></shdw><reflection type="none" /><glow type="none" spread="0"><clr><schemeClr val="accent1" /></clr></glow><softEdge type="none" spread="0" /><foreClr><schemeClr val="dk1" /></foreClr></bG><sldSz w="720" h="540" /><loc l="0" t="0" r="74" b="74" /><hLink enabled="false" trigG="00000000-0000-0000-0000-000000000000" /><fmtText></fmtText><dialData dialType="None" varG="00000000-0000-0000-0000-000000000000" defVarG="00000000-0000-0000-0000-000000000000" updateAction="drag" increment="1" rotation="180" rotationIndicatorOffsetDegrees="0" indicatorPaintMode="Always"><values start="0" end="12" /><rotationPoint xOffset="0" yOffset="0" /></dialData><picFormat tile="true" trans="0" rot="true"><offset l="0" t="0" r="0" b="0" /><tile x="0" y="0" scaleX="100" scaleY="100" align="1" mirror="Tile">Clamp</tile><sourceRect l="0" t="0" r="128" b="128" /><pic><brightness val="Normal" level="0" /><contrast val="Normal" level="0" /><recolor val="None"><clr /></recolor><blend mode="norm"><clr /></blend></pic></picFormat></pic></media><title></title><desc>&lt;Document xmlns:xsi="http://www.w3.org/2001/XMLSchema-instance" xmlns:xsd="http://www.w3.org/2001/XMLSchema"&gt;
  &lt;Content&gt;
    &lt;Block&gt;
      &lt;Style FlowDirection="LeftToRight" LeadingMargin="0" TrailingMargin="0" FirstLineMargin="0" Justification="Justify" LineSpacingRule="Multiple" LineSpacing="20" SpacingBefore="0" SpacingAfter="0"&gt;
        &lt;ListStyle ListType="None" ListTypeFormat="Parentheses" BulletFont="Arial" /&gt;
      &lt;/Style&gt;
      &lt;Span Text="Sí, la verdad es que cuando salgo con los amigos, que siempre"&gt;
        &lt;Style FontFamily="Open Sans" FontSize="8.64" FontIsBold="False" FontIsItalic="False" FontIsUnderline="False" FontIsStrikeout="False" ForegroundColor="#FFFFFF" /&gt;
      &lt;/Span&gt;
      &lt;Span Text=" llevo lentillas"&gt;
        &lt;Style FontFamily="Open Sans" FontSize="8.64" FontIsBold="True" FontIsItalic="False" FontIsUnderline="False" FontIsStrikeout="False" ForegroundColor="#FFFF00" LinkColor="#FFFF00" /&gt;
      &lt;/Span&gt;
      &lt;Span Text=", me noto peor. La tablet constantemente porque la uso tanto para estudiar como para chatear."&gt;
        &lt;Style FontFamily="Open Sans" FontSize="8.64" FontIsBold="False" FontIsItalic="False" FontIsUnderline="False" FontIsStrikeout="False" ForegroundColor="#FFFFFF" /&gt;
      &lt;/Span&gt;
    &lt;/Block&gt;
  &lt;/Content&gt;
&lt;/Document&gt;</desc><ttlShp g="3884b995-eb16-4eed-8e84-ff50d5750db8" verG="803e1b7d-f362-4e7b-a31a-9ef32db9a80e" timeManagerVisibilityLocked="false" typeName="" id="0" name="Text Box" state="106759" zOrder="-1" editCtx="Normal" initState="" handCur="true" rot="-1" acc="true" autoFit="resize" shdw="false" wrap="true" rtl="false" defHorzAlign="l" horzAlign="l" vertAlign="m" textDir="horz"><tmProps g="91509681-abe7-49eb-b91c-2b8345c851f8" verG="9e636849-4605-4dc4-b065-9f5ebc73a40b" cur="0" min="5000" visible="true" hideAll="false" /><tmCtxLst version="1"><txtTmCtx g="c17d52d0-5e48-45af-913a-ec8b19bc4aa7" verG="c771169e-43df-40fe-90c2-23a91a4dd217" start="0" dur="3000" min="250" max="0" hasMax="false" alwysShw="false" untilEnd="false" assetStart="0" name="" /></tmCtxLst><animEffect /><childLst /><trigLst /><stateLst /><bG shine="false"><noFill /><noLine /><lineStyle w="3" scale="1" cap="flat" join="rnd" dash="sld" cmpnd="sng"><arrow scale="1"><begin type="none" sz="size5" /><end type="none" sz="size5" /></arrow></lineStyle><gradOvrlyFill type="lin" style="lin" rot="true" angle="90" blendMode="ovrly" alpha="1" scale="1" reverse="false" adjustY="0" overlayFillType="None"><centerPt x="1" y="1" /><fillRect l="0" t="0" r="0" b="0" /><stops /></gradOvrlyFill><shdw sz="100" blur="4" angle="90" dist="4"><preset val="noShdw" mode="noShdw" /><clr><srgbClr val="000000" /><alpha val="60000" /></clr></shdw><reflection type="none" /><glow type="none" spread="0"><clr><schemeClr val="accent1" /></clr></glow><softEdge type="none" spread="0" /><foreClr><schemeClr val="dk1" /></foreClr><defaultFont sz="10" style="Bold" /></bG><sldSz w="720" h="540" /><loc l="0" t="0" r="3" b="10" /><hLink enabled="false" trigG="00000000-0000-0000-0000-000000000000" /><fmtText></fmtText><ph type="title" /><dialData dialType="None" varG="00000000-0000-0000-0000-000000000000" defVarG="00000000-0000-0000-0000-000000000000" updateAction="drag" increment="1" rotation="180" rotationIndicatorOffsetDegrees="0" indicatorPaintMode="Always"><values start="0" end="12" /><rotationPoint xOffset="0" yOffset="0" /></dialData><textMargin l="0" t="0" r="0" b="0" /><bounds l="0" t="0" r="0" b="0" /><resize fontNm="" fontSz="0" /><margins l="0" t="0" r="0" b="0" /><parLst /><plain></plain><hLinkLst /></ttlShp><descShp g="eca647a5-320e-4324-b14b-41e556ef7ca5" verG="4f15e988-810c-4e59-b427-b8e0e77d3112" timeManagerVisibilityLocked="false" typeName="" id="0" name="Text Box" state="106759" zOrder="0" editCtx="Normal" initState="" handCur="true" rot="-1" acc="true" parentG="3f400b97-9c27-44b5-a618-a38af8a3ec9d" autoFit="resize" shdw="false" wrap="true" rtl="false" defHorzAlign="l" horzAlign="l" vertAlign="t" textDir="horz"><tmProps g="bb64a925-4588-4e30-9fd7-d66178f50165" verG="7dd33307-dd68-4f02-a002-23733a3a3b36" cur="0" min="5000" visible="true" hideAll="false" /><tmCtxLst version="1"><txtTmCtx g="f2d87672-c6c6-40a3-8688-fd5d095a3dd4" verG="a52e496a-f1ed-49e2-83f6-251d27534fc7" start="0" dur="3000" min="250" max="0" hasMax="false" alwysShw="false" untilEnd="false" assetStart="0" name="" /></tmCtxLst><animEffect /><childLst /><trigLst /><stateLst /><bG shine="false"><noFill /><noLine /><lineStyle w="3" scale="1" cap="flat" join="rnd" dash="sld" cmpnd="sng"><arrow scale="1"><begin type="none" sz="size5" /><end type="none" sz="size5" /></arrow></lineStyle><gradOvrlyFill type="lin" style="lin" rot="true" angle="90" blendMode="ovrly" alpha="1" scale="1" reverse="false" adjustY="0" overlayFillType="None"><centerPt x="1" y="1" /><fillRect l="0" t="0" r="0" b="0" /><stops /></gradOvrlyFill><shdw sz="100" blur="4" angle="90" dist="4"><preset val="noShdw" mode="noShdw" /><clr><srgbClr val="000000" /><alpha val="60000" /></clr></shdw><reflection type="none" /><glow type="none" spread="0"><clr><schemeClr val="accent1" /></clr></glow><softEdge type="none" spread="0" /><foreClr><schemeClr val="dk1" /></foreClr><defaultFont sz="8.25" style="Regular" /></bG><sldSz w="1000" h="580" /><loc l="42" t="242" r="378" b="350" /><hLink enabled="false" trigG="00000000-0000-0000-0000-000000000000" /><fmtText></fmtText><ph type="body" /><dialData dialType="None" varG="00000000-0000-0000-0000-000000000000" defVarG="00000000-0000-0000-0000-000000000000" updateAction="drag" increment="1" rotation="180" rotationIndicatorOffsetDegrees="0" indicatorPaintMode="Always"><values start="0" end="12" /><rotationPoint xOffset="0" yOffset="0" /></dialData><textMargin l="0" t="0" r="0" b="0" /><bounds l="0" t="0" r="278" b="108" /><resize fontNm="" fontSz="0" /><margins l="0" t="0" r="0" b="0" /><parLst /><plain>Sí, la verdad es que cuando salgo con los amigos, que siempre llevo lentillas, me noto peor. La tablet constantemente porque la uso tanto para estudiar como para chatear.</plain><hLinkLst /></descShp></markerProps></marker><btn g="46878305-d980-43ad-a601-aba31aefcf98" verG="ef80d284-071b-4b9e-bd3f-41526e1da664" timeManagerVisibilityLocked="false" typeName="" id="1" name="Botón" state="107271" zOrder="8" editCtx="Normal" initState="Hidden" handCur="true" rot="-1" acc="true" autoFit="shrink" shdw="false" wrap="true" rtl="false" defHorzAlign="c" horzAlign="c" vertAlign="m" textDir="horz" style="def" defTxtShdw="False"><tmProps g="5e270c69-facc-478c-a640-a00c8a46930c" verG="fb31443d-b183-4515-902b-14a6b88f56a4" cur="0" min="5000" visible="true" hideAll="false" /><tmCtxLst version="2"><txtTmCtx g="74fa7b40-d32f-407c-9651-b33622feab26" verG="7f2a57ca-6f5c-4eba-a444-cd84bed15fc9" start="0" dur="10000" min="250" max="0" hasMax="false" alwysShw="false" untilEnd="true" assetStart="0" name="" /></tmCtxLst><animEffect /><childLst /><trigLst><trig g="46541cf7-32e2-4b0d-b1c0-d8848361e8a0" verG="07a63637-a77a-417c-82bb-f44ddea07330" name="Navigation" type="user" edit="variablename, subslides, keypresskeys, actions, operators, variablevalue, variableoperators" group="next" copiedG="46878305-d980-43ad-a601-aba31aefcf98"><data enabled="true" event="OnNextButtonClick" action="jumpToSlide" actSubType="next" NavigationIntent="Next" NavigationState="Button, Gesture"><keyPress keys="None" case="false" /><slide showNav="false" /><scene /><shape setStateName="" stateInclude="all" statesNot="are" stateName=""><stateLst /><dropLst /><intersectLst /><stopIntersectLst /><hoverLst /></shape><clickLst /><sldLayer /><video /><audio /><other open="" email="" js="" op="ass" varVal1="" useVar="false" dblVal="0" boolVal="True" positiveCompletion="true" time="PT0S" cuePoint="0" useRandom="false" randomMin="0" randomMax="0" /><interaction /><SeekTimeline target="00000000-0000-0000-0000-000000000000" timeSeconds="0" cuePoint="-1" variableReference="false" useRelativeTime="false" relativeTime="NaN" modifyPlaybackState="false" playbackState="Play" /><frame restore="true" /></data><condLst /></trig></trigLst><stateLst><state g="5d8c5c0c-7a02-4c9d-87cf-9f25de461980" verG="5ec399bc-adb3-4979-8348-ce81ed9d61cf" timeManagerVisibilityLocked="false" typeName="" id="0" state="2" showMasterSp="false" name="Normal" role="" resetMode="auto" layoutG="7f817a98-1fec-49af-97a0-9a010cd18ba4" stateG="00000000-0000-0000-0000-000000000000" showPlay="false" clrScheme="def" isDrawingThemeUpgraded="true" defG="f1d73aa8-f460-4914-b11e-150dfd1a4a20"><tmProps g="f1812d87-43c8-4514-a8a7-a8f41855d2b4" verG="3f826f59-2877-4914-ad96-d591baf1df42" cur="0" min="10000" visible="true" hideAll="false" /><tmCtxLst version="1"><tmCtx g="797f06c6-23b9-42cb-afdf-e5ccb6e6d05d" verG="5a7b5e40-fe98-48a8-a457-347e69ddf594" start="0" dur="0" min="250" max="0" hasMax="false" alwysShw="false" untilEnd="false" assetStart="0" name="" /></tmCtxLst><sz w="0" h="0" /><trans /><bg shine="false"><noFill /><noLine /><gradOvrlyFill type="def" style="def" rot="none" angle="3.40282347E+38" blendMode="def" alpha="-1" scale="-1" reverse="none" adjustY="-2147483648" overlayFillType="None"><centerPt x="-1" y="-1" /><fillRect l="0" t="0" r="0" b="0" /><stops /></gradOvrlyFill><reflection type="none" /><glow type="none" spread="0"><clr><schemeClr val="accent1" /></clr></glow><softEdge type="none" spread="0" /><foreClr><schemeClr val="dk1" /></foreClr></bg><shapeLst><btn g="f1d73aa8-f460-4914-b11e-150dfd1a4a20" verG="eebcaae0-7928-4313-8c3a-c8cdc443c88c" timeManagerVisibilityLocked="false" typeName="" id="2" name="Botón" state="40967" zOrder="0" editCtx="Normal" initState="" handCur="true" rot="-1" acc="true" autoFit="shrink" shdw="false" wrap="true" rtl="false" defHorzAlign="c" horzAlign="c" vertAlign="m" textDir="horz" style="def" defTxtShdw="False"><tmProps g="5e270c69-facc-478c-a640-a00c8a46930c" verG="fb31443d-b183-4515-902b-14a6b88f56a4" cur="0" min="5000" visible="true" hideAll="false" /><tmCtxLst version="2"><txtTmCtx g="74fa7b40-d32f-407c-9651-b33622feab26" verG="7f2a57ca-6f5c-4eba-a444-cd84bed15fc9" start="0" dur="10000" min="250" max="0" hasMax="false" alwysShw="false" untilEnd="true" assetStart="0" name="" /></tmCtxLst><animEffect /><childLst /><trigLst /><stateLst /><bG shine="false"><solidFill><clr><srgbClr val="078A9E" /></clr></solidFill><solidLine><clr><srgbClr val="078A9E" /></clr></solidLine><lineStyle w="1" scale="1" cap="flat" join="rnd" dash="sld" cmpnd="sng"><arrow scale="1"><begin type="none" sz="size5" /><end type="none" sz="size5" /></arrow></lineStyle><gradOvrlyFill type="lin" style="lin" rot="true" angle="90" blendMode="ovrly" alpha="1" scale="1" reverse="false" adjustY="0" overlayFillType="None"><centerPt x="1" y="1" /><fillRect l="0" t="0" r="0" b="0" /><stops /></gradOvrlyFill><shdw sz="100" blur="5" angle="45" dist="4"><preset val="offBr" mode="offBr" /><clr><srgbClr val="000000" /><alpha val="30196" /></clr></shdw><reflection type="none" /><glow type="none" spread="0"><clr><schemeClr val="accent1" /></clr></glow><softEdge type="none" spread="0" /><foreClr><schemeClr val="lt1" /></foreClr><defaultFont sz="14" style="Bold" /></bG><sldSz w="1000" h="580" /><loc l="0" t="0" r="162" b="46" /><hLink enabled="false" trigG="00000000-0000-0000-0000-000000000000" /><text>&lt;Document xmlns:xsi="http://www.w3.org/2001/XMLSchema-instance" xmlns:xsd="http://www.w3.org/2001/XMLSchema"&gt;
  &lt;Content&gt;
    &lt;Block&gt;
      &lt;Span Text="SIGUIENTE" /&gt;
    &lt;/Block&gt;
  &lt;/Content&gt;
&lt;/Document&gt;</text><fmtText>&lt;Document xmlns:xsi="http://www.w3.org/2001/XMLSchema-instance" xmlns:xsd="http://www.w3.org/2001/XMLSchema"&gt;
  &lt;Content&gt;
    &lt;Block&gt;
      &lt;Style FlowDirection="LeftToRight" LeadingMargin="0" TrailingMargin="0" FirstLineMargin="0" Justification="Center" DefaultTabStop="48" CustomTabStops="" ListLevel="0" LineSpacingRule="Multiple" LineSpacing="20" SpacingBefore="0" SpacingAfter="0"&gt;
        &lt;BaseSpanStyle FontFamily="+minor" FontSize="14" FontIsBold="True" FontIsItalic="False" FontIsUnderline="False" FontIsStrikeout="False" UnderlineStyle="Normal" ForegroundColor="lt1,00" BackgroundColor="#000000,00" UnderlineColor="#000000,00" Elevation="Normal" Spacing="0" IgnoreKerningTable="False" DisplayCase="AsIs" LanguageId="0" LinkColor="#0000FF"&gt;
          &lt;Shadow Offset="0x0" Color="#FFFFFF,00" /&gt;
        &lt;/BaseSpanStyle&gt;
        &lt;ListStyle ListType="None" ListTypeFormat="Plain" Start="0" Color="#000000,00" Size="100" /&gt;
      &lt;/Style&gt;
      &lt;Span Text="SIGUIENTE"&gt;
        &lt;Style FontFamily="Open Sans" FontSize="14" FontIsBold="True" FontIsItalic="False" FontIsUnderline="False" FontIsStrikeout="False" UnderlineStyle="Normal" ForegroundColor="#FFFFFF" BackgroundColor="#000000,00" UnderlineColor="#000000,00" Elevation="Normal" Spacing="0" IgnoreKerningTable="False" DisplayCase="AsIs" LanguageId="0" LinkColor="#0000FF"&gt;
          &lt;Shadow Offset="0x0" Color="#FFFFFF,00" /&gt;
        &lt;/Style&gt;
      &lt;/Span&gt;
    &lt;/Block&gt;
  &lt;/Content&gt;
&lt;/Document&gt;</fmtText><prstGeom><button vertexSet="false" /></prstGeom><dialData dialType="None" varG="00000000-0000-0000-0000-000000000000" defVarG="00000000-0000-0000-0000-000000000000" updateAction="drag" increment="1" rotation="180" rotationIndicatorOffsetDegrees="0" indicatorPaintMode="Always"><values start="0" end="12" /><rotationPoint xOffset="0" yOffset="0" /></dialData><textMargin l="4" t="2" r="4" b="2" /><bounds l="4" t="2" r="158" b="44" /><resize fontNm="" fontSz="0" /><margins l="0" t="0" r="0" b="0" /><parLst /><plain>SIGUIENTE</plain><hLinkLst /><pict val="Default" align="def"><clr /></pict></btn></shapeLst><trigLst /><text></text><shapeSz w="0" h="0" /></state><state g="31cf614f-e116-4c3b-91f7-488aa8388094" verG="526f3adf-1f1e-45ad-b3b8-395a02c13b45" timeManagerVisibilityLocked="false" typeName="" id="0" state="2" showMasterSp="false" name="Hover" role="" resetMode="auto" layoutG="7f817a98-1fec-49af-97a0-9a010cd18ba4" stateG="00000000-0000-0000-0000-000000000000" showPlay="false" clrScheme="def" isDrawingThemeUpgraded="true" defG="ce7ca69a-25b4-4f04-badc-c9365302194d"><tmProps g="c27ac503-6ebf-4184-834e-b688b9f36fea" verG="be30bcca-5b18-48e0-80a2-872fd6e97348" cur="0" min="10000" visible="true" hideAll="false" /><tmCtxLst version="1"><tmCtx g="2c548750-81e9-41af-ad53-dcb5c14f82da" verG="87bdd5c4-fac8-41b9-b748-8e44021cdc73" start="0" dur="0" min="250" max="0" hasMax="false" alwysShw="false" untilEnd="false" assetStart="0" name="" /></tmCtxLst><sz w="0" h="0" /><trans /><bg clrSchmOvr="lt" shine="false"><solidFill><clr /></solidFill><solidLine><clr /></solidLine><gradOvrlyFill type="def" style="def" rot="none" angle="3.40282347E+38" blendMode="def" alpha="-1" scale="-1" reverse="none" adjustY="-2147483648" overlayFillType="None"><centerPt x="-1" y="-1" /><fillRect l="0" t="0" r="0" b="0" /><stops /></gradOvrlyFill><reflection type="none" /><glow type="none" spread="0"><clr><schemeClr val="accent1" /></clr></glow><softEdge type="none" spread="0" /><foreClr><schemeClr val="lt1" /></foreClr><defaultFont style="Bold" /></bg><shapeLst><btn g="ce7ca69a-25b4-4f04-badc-c9365302194d" verG="1a37310c-1b7d-402d-a489-73c216758157" timeManagerVisibilityLocked="false" typeName="" id="3" name="Botón" state="32775" zOrder="0" editCtx="Normal" initState="" handCur="true" rot="-1" acc="true" autoFit="shrink" shdw="false" wrap="true" rtl="false" defHorzAlign="c" horzAlign="c" vertAlign="m" textDir="horz" style="def" defTxtShdw="False"><tmProps g="5e270c69-facc-478c-a640-a00c8a46930c" verG="fb31443d-b183-4515-902b-14a6b88f56a4" cur="0" min="5000" visible="true" hideAll="false" /><tmCtxLst version="2"><txtTmCtx g="74fa7b40-d32f-407c-9651-b33622feab26" verG="7f2a57ca-6f5c-4eba-a444-cd84bed15fc9" start="0" dur="10000" min="250" max="0" hasMax="false" alwysShw="false" untilEnd="true" assetStart="0" name="" /></tmCtxLst><animEffect /><childLst /><trigLst /><stateLst /><bG clrSchmOvr="lt" shine="false"><solidFill><clr><schemeClr val="custom1" /><tint val="85000" /></clr></solidFill><solidLine><clr><schemeClr val="custom1" /><shade val="50000" /></clr></solidLine><lineStyle w="1" scale="1" cap="flat" join="rnd" dash="sld" cmpnd="sng"><arrow scale="1"><begin type="none" sz="size5" /><end type="none" sz="size5" /></arrow></lineStyle><gradOvrlyFill type="lin" style="lin" rot="true" angle="90" blendMode="ovrly" alpha="1" scale="1" reverse="false" adjustY="0" overlayFillType="None"><centerPt x="1" y="1" /><fillRect l="0" t="0" r="0" b="0" /><stops /></gradOvrlyFill><shdw sz="100" blur="5" angle="45" dist="4"><preset val="offBr" mode="offBr" /><clr><srgbClr val="000000" /><alpha val="30196" /></clr></shdw><reflection type="none" /><glow type="none" spread="0"><clr><schemeClr val="accent1" /></clr></glow><softEdge type="none" spread="0" /><foreClr><schemeClr val="lt1" /></foreClr><defaultFont style="Bold" /></bG><sldSz w="1000" h="580" /><loc l="0" t="0" r="150" b="40" /><hLink enabled="false" trigG="00000000-0000-0000-0000-000000000000" /><fmtText></fmtText><prstGeom><button vertexSet="false" /></prstGeom><dialData dialType="None" varG="00000000-0000-0000-0000-000000000000" defVarG="00000000-0000-0000-0000-000000000000" updateAction="drag" increment="1" rotation="180" rotationIndicatorOffsetDegrees="0" indicatorPaintMode="Always"><values start="0" end="12" /><rotationPoint xOffset="0" yOffset="0" /></dialData><textMargin l="4" t="2" r="4" b="2" /><bounds l="4" t="2" r="158" b="44" /><resize fontNm="" fontSz="0" /><margins l="0" t="0" r="0" b="0" /><parLst /><plain>SIGUIENTE</plain><hLinkLst /><pict val="Default" align="def"><clr /></pict></btn></shapeLst><trigLst /><text></text><shapeSz w="0" h="0" /></state><state g="21e0528f-7843-4495-af2e-66d9d99212e6" verG="64e09609-3a0b-4889-8e10-fb3c71bb6601" timeManagerVisibilityLocked="false" typeName="" id="0" state="2" showMasterSp="false" name="Down" role="" resetMode="auto" layoutG="7f817a98-1fec-49af-97a0-9a010cd18ba4" stateG="00000000-0000-0000-0000-000000000000" showPlay="false" clrScheme="def" isDrawingThemeUpgraded="true" defG="b9cfe419-8e94-4c48-b8da-412cd8313128"><tmProps g="4f599637-af29-4e51-8471-b5d958ef2f0f" verG="383ee95b-9a24-4de5-b8b8-82eb51d6f0ac" cur="0" min="10000" visible="true" hideAll="false" /><tmCtxLst version="1"><tmCtx g="d509ab9b-095d-4894-b7eb-bf6f33683034" verG="35a763f5-935e-4922-852f-53f1b1f365e8" start="0" dur="0" min="250" max="0" hasMax="false" alwysShw="false" untilEnd="false" assetStart="0" name="" /></tmCtxLst><sz w="0" h="0" /><trans /><bg clrSchmOvr="lt" shine="false"><solidFill><clr /></solidFill><solidLine><clr /></solidLine><gradOvrlyFill type="def" style="def" rot="none" angle="3.40282347E+38" blendMode="def" alpha="-1" scale="-1" reverse="none" adjustY="-2147483648" overlayFillType="None"><centerPt x="-1" y="-1" /><fillRect l="0" t="0" r="0" b="0" /><stops /></gradOvrlyFill><reflection type="none" /><glow type="none" spread="0"><clr><schemeClr val="accent1" /></clr></glow><softEdge type="none" spread="0" /><foreClr><schemeClr val="lt1" /></foreClr><defaultFont style="Bold" /></bg><shapeLst><btn g="b9cfe419-8e94-4c48-b8da-412cd8313128" verG="b808f892-4cec-4a59-8b5d-2e6993a65bc5" timeManagerVisibilityLocked="false" typeName="" id="3" name="Botón" state="32775" zOrder="0" editCtx="Normal" initState="" handCur="true" rot="-1" acc="true" autoFit="shrink" shdw="false" wrap="true" rtl="false" defHorzAlign="c" horzAlign="c" vertAlign="m" textDir="horz" style="def" defTxtShdw="False"><tmProps g="5e270c69-facc-478c-a640-a00c8a46930c" verG="fb31443d-b183-4515-902b-14a6b88f56a4" cur="0" min="5000" visible="true" hideAll="false" /><tmCtxLst version="2"><txtTmCtx g="74fa7b40-d32f-407c-9651-b33622feab26" verG="7f2a57ca-6f5c-4eba-a444-cd84bed15fc9" start="0" dur="10000" min="250" max="0" hasMax="false" alwysShw="false" untilEnd="true" assetStart="0" name="" /></tmCtxLst><animEffect /><childLst /><trigLst /><stateLst /><bG clrSchmOvr="lt" shine="false"><solidFill><clr><schemeClr val="custom1" /><shade val="75000" /></clr></solidFill><solidLine><clr><schemeClr val="custom1" /><shade val="50000" /></clr></solidLine><lineStyle w="1" scale="1" cap="flat" join="rnd" dash="sld" cmpnd="sng"><arrow scale="1"><begin type="none" sz="size5" /><end type="none" sz="size5" /></arrow></lineStyle><gradOvrlyFill type="lin" style="lin" rot="true" angle="90" blendMode="ovrly" alpha="1" scale="1" reverse="false" adjustY="0" overlayFillType="None"><centerPt x="1" y="1" /><fillRect l="0" t="0" r="0" b="0" /><stops /></gradOvrlyFill><shdw sz="100" blur="5" angle="45" dist="4"><preset val="offBr" mode="offBr" /><clr><srgbClr val="000000" /><alpha val="30196" /></clr></shdw><reflection type="none" /><glow type="none" spread="0"><clr><schemeClr val="accent1" /></clr></glow><softEdge type="none" spread="0" /><foreClr><schemeClr val="lt1" /></foreClr><defaultFont style="Bold" /></bG><sldSz w="1000" h="580" /><loc l="0" t="0" r="150" b="40" /><hLink enabled="false" trigG="00000000-0000-0000-0000-000000000000" /><fmtText></fmtText><prstGeom><button vertexSet="false" /></prstGeom><dialData dialType="None" varG="00000000-0000-0000-0000-000000000000" defVarG="00000000-0000-0000-0000-000000000000" updateAction="drag" increment="1" rotation="180" rotationIndicatorOffsetDegrees="0" indicatorPaintMode="Always"><values start="0" end="12" /><rotationPoint xOffset="0" yOffset="0" /></dialData><textMargin l="4" t="2" r="4" b="2" /><bounds l="4" t="2" r="158" b="44" /><resize fontNm="" fontSz="0" /><margins l="0" t="0" r="0" b="0" /><parLst /><plain>SIGUIENTE</plain><hLinkLst /><pict val="Default" align="def"><clr /></pict></btn></shapeLst><trigLst /><text></text><shapeSz w="0" h="0" /></state><state g="06cdeb60-0ea4-46e2-856b-1815e111937e" verG="18745a72-4090-463f-96cf-37b16431f26d" timeManagerVisibilityLocked="false" typeName="" id="0" state="2" showMasterSp="false" name="Visited" role="" resetMode="auto" layoutG="7f817a98-1fec-49af-97a0-9a010cd18ba4" stateG="00000000-0000-0000-0000-000000000000" showPlay="false" clrScheme="def" isDrawingThemeUpgraded="true" defG="8c65bf13-2d65-4e3b-94b6-40b85b10e684"><tmProps g="b9e1e96b-4367-4200-8a23-a61ff41df6d6" verG="b7c7bf2d-9696-4e09-b969-6ca98d700c4c" cur="0" min="10000" visible="true" hideAll="false" /><tmCtxLst version="1"><tmCtx g="d0679c79-30dd-44ed-98df-3d61072220a6" verG="cc7ee805-5f0f-454c-a645-2883e10a899d" start="0" dur="0" min="250" max="0" hasMax="false" alwysShw="false" untilEnd="false" assetStart="0" name="" /></tmCtxLst><sz w="0" h="0" /><trans /><bg clrSchmOvr="lt" shine="false"><solidFill><clr /></solidFill><solidLine><clr /></solidLine><gradOvrlyFill type="def" style="def" rot="none" angle="3.40282347E+38" blendMode="def" alpha="-1" scale="-1" reverse="none" adjustY="-2147483648" overlayFillType="None"><centerPt x="-1" y="-1" /><fillRect l="0" t="0" r="0" b="0" /><stops /></gradOvrlyFill><reflection type="none" /><glow type="none" spread="0"><clr><schemeClr val="accent1" /></clr></glow><softEdge type="none" spread="0" /><foreClr><schemeClr val="lt1" /></foreClr><defaultFont style="Bold" /></bg><shapeLst><btn g="8c65bf13-2d65-4e3b-94b6-40b85b10e684" verG="a765ce8b-2612-4ba5-8610-2ef976dd403f" timeManagerVisibilityLocked="false" typeName="" id="3" name="Botón" state="32775" zOrder="0" editCtx="Normal" initState="" handCur="true" rot="-1" acc="true" autoFit="shrink" shdw="false" wrap="true" rtl="false" defHorzAlign="c" horzAlign="c" vertAlign="m" textDir="horz" style="def" defTxtShdw="False"><tmProps g="5e270c69-facc-478c-a640-a00c8a46930c" verG="fb31443d-b183-4515-902b-14a6b88f56a4" cur="0" min="5000" visible="true" hideAll="false" /><tmCtxLst version="2"><txtTmCtx g="74fa7b40-d32f-407c-9651-b33622feab26" verG="7f2a57ca-6f5c-4eba-a444-cd84bed15fc9" start="0" dur="10000" min="250" max="0" hasMax="false" alwysShw="false" untilEnd="true" assetStart="0" name="" /></tmCtxLst><animEffect /><childLst /><trigLst /><stateLst /><bG clrSchmOvr="lt" shine="false"><solidFill><clr><schemeClr val="custom1" /></clr></solidFill><solidLine><clr><schemeClr val="custom1" /><shade val="50000" /></clr></solidLine><lineStyle w="1" scale="1" cap="flat" join="rnd" dash="sld" cmpnd="sng"><arrow scale="1"><begin type="none" sz="size5" /><end type="none" sz="size5" /></arrow></lineStyle><gradOvrlyFill type="lin" style="lin" rot="true" angle="90" blendMode="ovrly" alpha="1" scale="1" reverse="false" adjustY="0" overlayFillType="None"><centerPt x="1" y="1" /><fillRect l="0" t="0" r="0" b="0" /><stops /></gradOvrlyFill><shdw sz="100" blur="5" angle="45" dist="4"><preset val="offBr" mode="offBr" /><clr><srgbClr val="000000" /><alpha val="30196" /></clr></shdw><reflection type="none" /><glow type="none" spread="0"><clr><schemeClr val="accent1" /></clr></glow><softEdge type="none" spread="0" /><foreClr><schemeClr val="lt1" /></foreClr><defaultFont style="Bold" /></bG><sldSz w="1000" h="580" /><loc l="0" t="0" r="150" b="40" /><hLink enabled="false" trigG="00000000-0000-0000-0000-000000000000" /><fmtText></fmtText><prstGeom><button vertexSet="false" /></prstGeom><dialData dialType="None" varG="00000000-0000-0000-0000-000000000000" defVarG="00000000-0000-0000-0000-000000000000" updateAction="drag" increment="1" rotation="180" rotationIndicatorOffsetDegrees="0" indicatorPaintMode="Always"><values start="0" end="12" /><rotationPoint xOffset="0" yOffset="0" /></dialData><textMargin l="4" t="2" r="4" b="2" /><bounds l="4" t="2" r="158" b="44" /><resize fontNm="" fontSz="0" /><margins l="0" t="0" r="0" b="0" /><parLst /><plain>SIGUIENTE</plain><hLinkLst /><pict val="Default" align="def"><clr /></pict></btn></shapeLst><trigLst /><text></text><shapeSz w="0" h="0" /></state><state g="90a3df96-593d-4935-a4f7-734a09a4b300" verG="97d4c206-4c71-453e-9d4f-e5f2045e3952" timeManagerVisibilityLocked="false" typeName="" id="0" state="2" showMasterSp="false" name="Disabled" role="" resetMode="auto" layoutG="7f817a98-1fec-49af-97a0-9a010cd18ba4" stateG="00000000-0000-0000-0000-000000000000" showPlay="false" clrScheme="def" isDrawingThemeUpgraded="true" defG="ff962a73-3fb5-421f-b1ac-e2b379a0c231"><tmProps g="17d8426d-09f9-4452-8b44-70776686f986" verG="648b0425-daa8-4a9c-90f3-cdd68e16bfeb" cur="0" min="10000" visible="true" hideAll="false" /><tmCtxLst version="1"><tmCtx g="4495e726-7c6a-4f43-b275-d6c99e2e5d3a" verG="1eb15b16-143f-481c-9870-269b024e1e1f" start="0" dur="0" min="250" max="0" hasMax="false" alwysShw="false" untilEnd="false" assetStart="0" name="" /></tmCtxLst><sz w="0" h="0" /><trans /><bg clrSchmOvr="lt" shine="false"><solidFill><clr /></solidFill><solidLine><clr /></solidLine><gradOvrlyFill type="def" style="def" rot="none" angle="3.40282347E+38" blendMode="def" alpha="-1" scale="-1" reverse="none" adjustY="-2147483648" overlayFillType="None"><centerPt x="-1" y="-1" /><fillRect l="0" t="0" r="0" b="0" /><stops /></gradOvrlyFill><reflection type="none" /><glow type="none" spread="0"><clr><schemeClr val="accent1" /></clr></glow><softEdge type="none" spread="0" /><foreClr><schemeClr val="lt1" /></foreClr><defaultFont style="Bold" /></bg><shapeLst><btn g="ff962a73-3fb5-421f-b1ac-e2b379a0c231" verG="6932fad1-33a1-4fa7-8b1e-c5542350f43a" timeManagerVisibilityLocked="false" typeName="" id="3" name="Botón" state="32775" zOrder="0" editCtx="Normal" initState="" handCur="true" rot="-1" acc="true" opac="50" autoFit="shrink" shdw="false" wrap="true" rtl="false" defHorzAlign="c" horzAlign="c" vertAlign="m" textDir="horz" style="def" defTxtShdw="False"><tmProps g="5e270c69-facc-478c-a640-a00c8a46930c" verG="fb31443d-b183-4515-902b-14a6b88f56a4" cur="0" min="5000" visible="true" hideAll="false" /><tmCtxLst version="2"><txtTmCtx g="74fa7b40-d32f-407c-9651-b33622feab26" verG="7f2a57ca-6f5c-4eba-a444-cd84bed15fc9" start="0" dur="10000" min="250" max="0" hasMax="false" alwysShw="false" untilEnd="true" assetStart="0" name="" /></tmCtxLst><animEffect /><childLst /><trigLst /><stateLst /><bG clrSchmOvr="lt" shine="false"><solidFill><clr><schemeClr val="custom1" /></clr></solidFill><solidLine><clr><schemeClr val="custom1" /><shade val="50000" /></clr></solidLine><lineStyle w="1" scale="1" cap="flat" join="rnd" dash="sld" cmpnd="sng"><arrow scale="1"><begin type="none" sz="size5" /><end type="none" sz="size5" /></arrow></lineStyle><gradOvrlyFill type="lin" style="lin" rot="true" angle="90" blendMode="ovrly" alpha="1" scale="1" reverse="false" adjustY="0" overlayFillType="None"><centerPt x="1" y="1" /><fillRect l="0" t="0" r="0" b="0" /><stops /></gradOvrlyFill><shdw sz="100" blur="5" angle="45" dist="4"><preset val="offBr" mode="offBr" /><clr><srgbClr val="000000" /><alpha val="30196" /></clr></shdw><reflection type="none" /><glow type="none" spread="0"><clr><schemeClr val="accent1" /></clr></glow><softEdge type="none" spread="0" /><foreClr><schemeClr val="lt1" /></foreClr><defaultFont style="Bold" /></bG><sldSz w="1000" h="580" /><loc l="0" t="0" r="150" b="40" /><hLink enabled="false" trigG="00000000-0000-0000-0000-000000000000" /><fmtText></fmtText><prstGeom><button vertexSet="false" /></prstGeom><dialData dialType="None" varG="00000000-0000-0000-0000-000000000000" defVarG="00000000-0000-0000-0000-000000000000" updateAction="drag" increment="1" rotation="180" rotationIndicatorOffsetDegrees="0" indicatorPaintMode="Always"><values start="0" end="12" /><rotationPoint xOffset="0" yOffset="0" /></dialData><textMargin l="4" t="2" r="4" b="2" /><bounds l="4" t="2" r="158" b="44" /><resize fontNm="" fontSz="0" /><margins l="0" t="0" r="0" b="0" /><parLst /><plain>SIGUIENTE</plain><hLinkLst /><pict val="Default" align="def"><clr /></pict></btn></shapeLst><trigLst /><text></text><shapeSz w="0" h="0" /></state></stateLst><bG shine="false"><noFill /><noLine /><lineStyle w="3" scale="1" cap="flat" join="rnd" dash="sld" cmpnd="sng"><arrow scale="1"><begin type="none" sz="size5" /><end type="none" sz="size5" /></arrow></lineStyle><gradOvrlyFill type="lin" style="lin" rot="true" angle="90" blendMode="ovrly" alpha="1" scale="1" reverse="false" adjustY="0" overlayFillType="None"><centerPt x="1" y="1" /><fillRect l="0" t="0" r="0" b="0" /><stops /></gradOvrlyFill><shdw sz="100" blur="4" angle="90" dist="4"><preset val="noShdw" mode="noShdw" /><clr><srgbClr val="000000" /><alpha val="60000" /></clr></shdw><reflection type="none" /><glow type="none" spread="0"><clr><schemeClr val="accent1" /></clr></glow><softEdge type="none" spread="0" /><foreClr><schemeClr val="dk1" /></foreClr></bG><sldSz w="1000" h="580" /><loc l="814" t="512" r="976" b="558" /><hLink enabled="false" trigG="00000000-0000-0000-0000-000000000000" /><fmtText></fmtText><propBag><prop><key>oldsize</key><val><sz w="1000" h="580" /></val></prop></propBag><prstGeom><button vertexSet="false" /></prstGeom><dialData dialType="None" varG="00000000-0000-0000-0000-000000000000" defVarG="00000000-0000-0000-0000-000000000000" updateAction="drag" increment="1" rotation="180" rotationIndicatorOffsetDegrees="0" indicatorPaintMode="Always"><values start="0" end="12" /><rotationPoint xOffset="0" yOffset="0" /></dialData><textMargin l="4" t="2" r="4" b="2" /><bounds l="0" t="0" r="0" b="0" /><resize fontNm="" fontSz="0" /><margins l="0" t="0" r="0" b="0" /><parLst /><hLinkLst /><pict val="Default" align="def"><clr /></pict></btn></shapeLst><trigLst><trig g="c5330bcc-54b1-4bcd-be3a-68e870f786ae" verG="062c58be-a59e-4b57-be85-cbc205514689" name="Navigation" type="user" edit="variablename, subslides, keypresskeys, actions, operators, variablevalue, variableoperators" group="next" copiedG="dbf73251-abaf-49e1-8df7-0623a291dc96"><data enabled="false" event="OnNextButtonClick" action="jumpToSlide" actSubType="next" NavigationIntent="Next" NavigationState="Button, Gesture"><keyPress keys="None" case="false" /><slide showNav="false" /><scene /><shape setStateName="" stateInclude="all" statesNot="are" stateName=""><stateLst /><dropLst /><intersectLst /><stopIntersectLst /><hoverLst /></shape><clickLst /><sldLayer /><video /><audio /><other open="" email="" js="" op="ass" varVal1="" useVar="false" dblVal="0" boolVal="True" positiveCompletion="true" time="PT0S" cuePoint="0" useRandom="false" randomMin="0" randomMax="0" /><interaction /><SeekTimeline target="00000000-0000-0000-0000-000000000000" timeSeconds="0" cuePoint="-1" variableReference="false" useRelativeTime="false" relativeTime="NaN" modifyPlaybackState="false" playbackState="Play" /><frame actionG="0ec0db78-2e1d-4919-bde6-6824587f77c4" restore="true" /></data><condLst /></trig><trig g="ae475cc5-601c-414e-82c1-df8dc7d39471" verG="31f7ff62-0ad7-4bcd-ba10-0695dd185511" name="Previous" type="user" edit="variablename, subslides, keypresskeys, actions, operators, variablevalue, variableoperators" group="none" copiedG="dbf73251-abaf-49e1-8df7-0623a291dc96"><data enabled="true" event="OnClick" action="jumpToSlide" actSubType="prev" NavigationIntent="Previous" NavigationState="Button, Gesture"><keyPress keys="None" case="false" /><slide showNav="false" /><scene /><shape setStateName="" stateInclude="all" statesNot="are" stateName=""><stateLst /><dropLst /><intersectLst /><stopIntersectLst /><hoverLst /></shape><clickLst /><sldLayer /><video /><audio /><other open="" email="" js="" op="ass" varVal1="" useVar="false" dblVal="0" boolVal="True" positiveCompletion="true" time="PT0S" cuePoint="0" useRandom="false" randomMin="0" randomMax="0" /><interaction /><SeekTimeline target="00000000-0000-0000-0000-000000000000" timeSeconds="0" cuePoint="-1" variableReference="false" useRelativeTime="false" relativeTime="NaN" modifyPlaybackState="false" playbackState="Play" /><frame actionG="ae475cc5-601c-414e-82c1-df8dc7d39471" restore="true" /></data><condLst /></trig></trigLst><propBag><prop><key>oldsize</key><val><sz w="1000" h="580" /></val></prop><prop><key>oldprojguid</key><val g="edf58a9c-188d-4948-a9fe-dabeea3937c3" /></prop></propBag><note></note><szCalc mode="scale" fillA="mc" v="3"><cropRect l="0" t="0" r="0" b="0" /><currSz w="1000" h="580" /><lastSz w="1000" h="580" /></szCalc><navData prev="true" prevGesture="true" next="true" nextGesture="true" submit="false" default="true" menu="false" res="true" glos="false" notes="false" seek="false" replay="false" play="false" search="false" ltBxClse="true" /><thumb g="b614993c-c39a-48b7-8416-5afb9dc9f17c" sz="300" /><panTime g="a456c9e3-6b4c-42e3-8c47-c7f45046e365" verG="aa50d828-687a-42e9-b544-add4a960bdbd" timeManagerVisibilityLocked="false" typeName="" hide="false" lock="false"><tmProps g="7190b3be-ef4c-48c2-9cd9-47921b27033e" verG="c4199a40-8e1a-43b6-b889-75121fbf4e86" cur="0" min="5000" visible="true" hideAll="false" /><tmCtxLst version="0" /></panTime><panRect g="b0b12fb0-42dd-427c-8f03-da4ad04b6a69"><rect l="0" t="0" r="0" b="0" /></panRect></sld>